Workbook

Sheet Resumen
A1: ESTADIO YAXCHÉ + PLAZA SAKBÉ — ¿Cuánto genera y cuándo se paga?
A2: Modelo financiero de concepto. Millones de pesos de 2026, sin inflación ni IVA. Tres escenarios: cambia cualquier número azul en "Supuestos" y todo se recalcula.
A5: Lo más importante | B5: Unidad | C5: Conservador | D5: Base | E5: Optimista
A6: Inversión de construcción (sin IVA, sin terreno) | B6: M MXN | C6: =Supuestos!$C$8 -> 53245 | D6: =Supuestos!$D$8 -> 53245 | E6: =Supuestos!$E$8 -> 53245
A7: Días de evento al año | B7: días | C7: =Eventos!$C$63 -> 42 | D7: =Eventos!$D$63 -> 58 | E7: =Eventos!$E$63 -> 77
A8: de ellos, conciertos | B8: conciertos | C8: =Eventos!$C$23 -> 8 | D8: =Eventos!$D$23 -> 12 | E8: =Eventos!$E$23 -> 18
A9: Asistentes a eventos al año | B9: personas | C9: =Eventos!$C$64 -> 2195000 | D9: =Eventos!$D$64 -> 3742000 | E9: =Eventos!$E$64 -> 5805000
A10: Ingresos del estadio | B10: M MXN/año | C10: =Ingresos!$C$66 -> 1147.8325 | D10: =Ingresos!$D$66 -> 2506.9224 | E10: =Ingresos!$E$66 -> 4829.6638
A11: Ingresos de la Plaza Sakbé | B11: M MXN/año | C11: =Ingresos!$C$67 -> 1340.6234 | D11: =Ingresos!$D$67 -> 1941.3497 | E11: =Ingresos!$E$67 -> 2640.9132
A12: Ingresos de energía y reciclaje | B12: M MXN/año | C12: =Ingresos!$C$65 -> 9.9101514 | D12: =Ingresos!$D$65 -> 18.165425 | E12: =Ingresos!$E$65 -> 28.928858
A13: INGRESOS TOTALES | B13: M MXN/año | C13: =Ingresos!$C$68 -> 2498.366 | D13: =Ingresos!$D$68 -> 4466.4375 | E13: =Ingresos!$E$68 -> 7499.5059
A14: Costos de operación | B14: M MXN/año | C14: =-Costos_Operacion!$C$42 -> -1881.5695 | D14: =-Costos_Operacion!$D$42 -> -1718.0966 | E14: =-Costos_Operacion!$E$42 -> -1627.9351
A15: EBITDA (lo que queda cada año) | B15: M MXN/año | C15: =Costos_Operacion!$C$46 -> 616.79651 | D15: =Costos_Operacion!$D$46 -> 2748.3409 | E15: =Costos_Operacion!$E$46 -> 5871.5708
A16: Margen | B16: % | C16: =Costos_Operacion!$C$47 -> 0.24687996 | D16: =Costos_Operacion!$D$47 -> 0.61533178 | E16: =Costos_Operacion!$E$47 -> 0.78292769
A17: Recuperación simple (inversión ÷ EBITDA) | B17: años | C17: =Supuestos!$C$8/Costos_Operacion!$C$46 -> 86.325067 | D17: =Supuestos!$D$8/Costos_Operacion!$D$46 -> 19.373506 | E17: =Supuestos!$E$8/Costos_Operacion!$E$46 -> 9.0682718
A18: Recuperación con flujo, después de impuestos | B18: años desde apertura | C18: =Flujo_30_anios!$B$22 -> más de 30 | D18: =Flujo_30_anios!$B$45 -> 20 | E18: =Flujo_30_anios!$B$68 -> 12
A19: TIR real antes de impuestos | B19: % | C19: =Flujo_30_anios!$B$20 -> -0.055436918 | D19: =Flujo_30_anios!$B$43 -> 0.026213253 | E19: =Flujo_30_anios!$B$66 -> 0.087628617
A20: TIR real después de impuestos | B20: % | C20: =Flujo_30_anios!$B$21 -> -0.063561192 | D20: =Flujo_30_anios!$B$44 -> 0.02013905 | E20: =Flujo_30_anios!$B$67 -> 0.069403752
A21: VPN a la tasa real (después de impuestos) | B21: M MXN | C21: =Flujo_30_anios!$B$19 -> -43123.864 | D21: =Flujo_30_anios!$B$42 -> -25058.117 | E21: =Flujo_30_anios!$B$65 -> -324.73558
A23: Energía | B23: Unidad | C23: Conservador | D23: Base | E23: Optimista
A24: Potencia solar instalada | B24: MWp | C24: =Energia!$C$16/1000 -> 12.58117 | D24: =Energia!$D$16/1000 -> 13.1109 | E24: =Energia!$E$16/1000 -> 13.64063
A25: Generación solar | B25: GWh/año | C25: =Energia!$C$20 -> 13.890757 | D25: =Energia!$D$20 -> 15.924749 | E25: =Energia!$E$20 -> 18.832145
A26: Energía solar que se pierde (calor, polvo, sombra, inversores, cables) | B26: GWh/año | C26: =Energia!$C$22 -> 5.1507079 | D26: =Energia!$D$22 -> 4.7737154 | E26: =Energia!$E$22 -> 4.1582029
A27: Consumo de todo el conjunto | B27: GWh/año | C27: =Energia!$C$31 -> 65.983664 | D27: =Energia!$D$31 -> 58.584957 | E27: =Energia!$E$31 -> 53.44767
A28: Estadio | B28: GWh/año | C28: =Energia!$C$27 -> 8.652 | D28: =Energia!$D$27 -> 8.594 | E28: =Energia!$E$27 -> 8.721
A29: Plaza Sakbé | B29: GWh/año | C29: =Energia!$C$28 -> 52.12134 | D29: =Energia!$D$28 -> 44.39966 | E29: =Energia!$E$28 -> 38.6084
A30: Estacionamiento y cargadores | B30: GWh/año | C30: =Energia!$C$29+Energia!$C$30 -> 5.210324 | D30: =Energia!$D$29+Energia!$D$30 -> 5.591297 | E30: =Energia!$E$29+Energia!$E$30 -> 6.11827
A31: Lo que cubren los paneles | B31: % | C31: =Energia!$C$34 -> 0.21051812 | D31: =Energia!$D$34 -> 0.27182318 | E31: =Energia!$E$34 -> 0.35234735
A32: La cubierta vs. lo que gasta el estadio | B32: % | C32: =Energia!$C$35 -> 1.2747673 | D32: =Energia!$D$35 -> 1.4718598 | E32: =Energia!$E$35 -> 1.7158242
A33: Energía que se compra a la red (todo el conjunto) | B33: GWh/año | C33: =Energia!$C$36 -> 52.092907 | D33: =Energia!$D$36 -> 42.660208 | E33: =Energia!$E$36 -> 34.615525
A34: Costo de esa energía (todo el conjunto) | B34: M MXN/año | C34: =Energia!$C$37 -> 161.48801 | D34: =Energia!$D$37 -> 119.44858 | E34: =Energia!$E$37 -> 86.538812
A35: de eso paga el dueño | B35: M MXN/año | C35: =Energia!$C$44 -> 56.463512 | D35: =Energia!$D$44 -> 38.6412 | E35: =Energia!$E$44 -> 23.800162
A36: y los locatarios en sus medidores | B36: M MXN/año | C36: =Energia!$C$45 -> 105.0245 | D36: =Energia!$D$45 -> 80.807381 | E36: =Energia!$E$45 -> 62.73865
A37: Ahorro por los paneles | B37: M MXN/año | C37: =Energia!$C$48 -> 43.061346 | D37: =Energia!$D$48 -> 44.589298 | E37: =Energia!$E$48 -> 47.080363
A38: Inversión solar (con indirectos) | B38: M MXN | C38: =Energia!$C$56 -> 819.80451 | D38: =Energia!$D$56 -> 823.84785 | E38: =Energia!$E$56 -> 827.89119
A39: Los paneles se pagan solos en (todo el sistema) | B39: años | C39: =Energia!$C$61 -> 19.488926 | D39: =Energia!$D$61 -> 17.875152 | E39: =Energia!$E$61 -> 15.956243
A40: solo los de la cubierta del estadio | B40: años | C40: =Energia!$C$57 -> 14.00178 | D40: =Energia!$D$57 -> 12.906556 | E40: =Energia!$E$57 -> 11.572945
A41: el vidrio solar de la fachada | B41: años | C41: =Energia!$C$59 -> 69.708548 | D41: =Energia!$D$59 -> 61.719309 | E41: =Energia!$E$59 -> 53.429503
A42: CO₂ evitado | B42: t/año | C42: =Energia!$C$51 -> 6084.1515 | D42: =Energia!$D$51 -> 6975.0402 | E42: =Energia!$E$51 -> 8248.4796
A43: Agua que no viene de la red (lluvia + reúso) | B43: % | C43: =Agua!$C$16 -> 0.4107736 | D43: =Agua!$D$16 -> 0.5304649 | E43: =Agua!$E$16 -> 0.65487656
A45: Si el gobierno pone la obra común (APP) | B45: Unidad | C45: Conservador | D45: Base | E45: Optimista
A46: Inversión privada | B46: M MXN | C46: =Supuestos!$C$8-Supuestos!$C$12*Supuestos!$C$23 -> 34929 | D46: =Supuestos!$D$8-Supuestos!$D$12*Supuestos!$D$23 -> 34929 | E46: =Supuestos!$E$8-Supuestos!$E$12*Supuestos!$E$23 -> 34929
A47: Recuperación simple | B47: años | C47: =(Supuestos!$C$8-Supuestos!$C$12*Supuestos!$C$23)/Costos_Operacion!$C$46 -> 56.629698 | D47: =(Supuestos!$D$8-Supuestos!$D$12*Supuestos!$D$23)/Costos_Operacion!$D$46 -> 12.709122 | E47: =(Supuestos!$E$8-Supuestos!$E$12*Supuestos!$E$23)/Costos_Operacion!$E$46 -> 5.948834
A48: TIR real después de impuestos | B48: % / M MXN | D48: =Flujo_30_anios!$B$90 -> 0.044712836
A49: VPN a la tasa real (después de impuestos) | B49: % / M MXN | D49: =Flujo_30_anios!$B$88 -> -10672.767
A50: Obra común = estacionamiento subterráneo, excavación, explanada y redes (18,316 M). Solo se calcula sobre el escenario Base.
A52: ¿Y si hay más conciertos? (escenario Base) | B52: Unidad | C52: EBITDA M MXN | D52: Recup. privada | E52: Recup. con APP
A53: 6 conciertos al año | B53: EBITDA / años | C53: =(Costos_Operacion!$D$46+(6-Supuestos!$D$36)*Ingresos!$D$79) -> 2478.7195 | D53: =Supuestos!$D$8/(Costos_Operacion!$D$46+(6-Supuestos!$D$36)*Ingresos!$D$79) -> 21.480849 | E53: =(Supuestos!$D$8-Supuestos!$D$12)/(Costos_Operacion!$D$46+(6-Supuestos!$D$36)*Ingresos!$D$79) -> 14.09155
A54: 12 conciertos al año | B54: EBITDA / años | C54: =(Costos_Operacion!$D$46+(12-Supuestos!$D$36)*Ingresos!$D$79) -> 2748.3409 | D54: =Supuestos!$D$8/(Costos_Operacion!$D$46+(12-Supuestos!$D$36)*Ingresos!$D$79) -> 19.373506 | E54: =(Supuestos!$D$8-Supuestos!$D$12)/(Costos_Operacion!$D$46+(12-Supuestos!$D$36)*Ingresos!$D$79) -> 12.709122
A55: 18 conciertos al año | B55: EBITDA / años | C55: =(Costos_Operacion!$D$46+(18-Supuestos!$D$36)*Ingresos!$D$79) -> 3017.9623 | D55: =Supuestos!$D$8/(Costos_Operacion!$D$46+(18-Supuestos!$D$36)*Ingresos!$D$79) -> 17.642699 | E55: =(Supuestos!$D$8-Supuestos!$D$12)/(Costos_Operacion!$D$46+(18-Supuestos!$D$36)*Ingresos!$D$79) -> 11.573703
A56: 24 conciertos al año | B56: EBITDA / años | C56: =(Costos_Operacion!$D$46+(24-Supuestos!$D$36)*Ingresos!$D$79) -> 3287.5837 | D56: =Supuestos!$D$8/(Costos_Operacion!$D$46+(24-Supuestos!$D$36)*Ingresos!$D$79) -> 16.195785 | E56: =(Supuestos!$D$8-Supuestos!$D$12)/(Costos_Operacion!$D$46+(24-Supuestos!$D$36)*Ingresos!$D$79) -> 10.62452
A57: 36 conciertos al año | B57: EBITDA / años | C57: =(Costos_Operacion!$D$46+(36-Supuestos!$D$36)*Ingresos!$D$79) -> 3826.8265 | D57: =Supuestos!$D$8/(Costos_Operacion!$D$46+(36-Supuestos!$D$36)*Ingresos!$D$79) -> 13.913617 | E57: =(Supuestos!$D$8-Supuestos!$D$12)/(Costos_Operacion!$D$46+(36-Supuestos!$D$36)*Ingresos!$D$79) -> 9.1274062
A58: ="Cada concierto extra deja ≈ "&TEXT(Ingresos!$D$79,"#,##0")&" M MXN netos al dueño. Más de 18 al año exige pasto híbrido y cubrecancha (ya incluidos)." -> Cada concierto extra deja ≈ 45 M MXN netos al dueño. Más de 18 al año exige pasto híbrido y cubrecancha (ya incluidos).
A60: Todas las fuentes de ingreso (escenario Base), de mayor a menor | B60: Unidad | C60: M MXN/año | D60: % del total
A61: Renta: tiendas | B61: Plaza Sakbé | C61: =Ingresos!$D$41 -> 609.81968 | D61: =C61/Ingresos!$D$68 -> 0.1365338
A62: Palcos (renta anual) | B62: Estadio: palcos y patrocinios | C62: =Ingresos!$D$24 -> 405 | D62: =C62/Ingresos!$D$68 -> 0.090676294
A63: Alimentos y bebidas (participación de la concesión) | B63: Estadio: gasto del público | C63: =Ingresos!$D$18 -> 387.616 | D63: =C63/Ingresos!$D$68 -> 0.086784154
A64: Renta: restaurantes y terrazas | B64: Plaza Sakbé | C64: =Ingresos!$D$42 -> 298.13406 | D64: =C64/Ingresos!$D$68 -> 0.066749857
A65: Renta: oficinas y coworking | B65: Plaza Sakbé | C65: =Ingresos!$D$46 -> 243.92787 | D65: =C65/Ingresos!$D$68 -> 0.05461352
A66: Renta por conciertos | B66: Estadio: eventos | C66: =Ingresos!$D$9 -> 242.88 | D66: =C66/Ingresos!$D$68 -> 0.05437891
A67: Cuota de mantenimiento de locatarios (CAM) | B67: Plaza Sakbé | C67: =Ingresos!$D$52 -> 230.37632 | D67: =C67/Ingresos!$D$68 -> 0.051579435
A68: Asientos club (membresía anual) | B68: Estadio: palcos y patrocinios | C68: =Ingresos!$D$25 -> 204 | D68: =C68/Ingresos!$D$68 -> 0.045673985
A69: Patrocinios oficiales y exclusividad de bebidas | B69: Estadio: palcos y patrocinios | C69: =Ingresos!$D$27 -> 150 | D69: =C69/Ingresos!$D$68 -> 0.033583813
A70: Comisión de boletaje (rebate) | B70: Estadio: eventos | C70: =Ingresos!$D$15 -> 136.908 | D70: =C70/Ingresos!$D$68 -> 0.030652618
A71: Estacionamiento diario (sin evento) | B71: Plaza Sakbé | C71: =Ingresos!$D$51 -> 125.72755 | D71: =C71/Ingresos!$D$68 -> 0.028149404
A72: Derechos de nombre del estadio | B72: Estadio: palcos y patrocinios | C72: =Ingresos!$D$26 -> 111 | D72: =C72/Ingresos!$D$68 -> 0.024852021
A73: Renta por partidos de fútbol de liga | B73: Estadio: eventos | C73: =Ingresos!$D$7 -> 100.224 | D73: =C73/Ingresos!$D$68 -> 0.02243936
A74: Renta: clínica, guardería y museo | B74: Plaza Sakbé | C74: =Ingresos!$D$45 -> 94.860839 | D74: =C74/Ingresos!$D$68 -> 0.021238591
A75: Renta por festivales | B75: Estadio: eventos | C75: =Ingresos!$D$11 -> 90 | D75: =C75/Ingresos!$D$68 -> 0.020150288
A76: Cuota de instalación por boleto | B76: Estadio: eventos | C76: =Ingresos!$D$14 -> 88.1 | D76: =C76/Ingresos!$D$68 -> 0.019724893
A77: Paquetes VIP y hospitalidad por evento | B77: Estadio: gasto del público | C77: =Ingresos!$D$20 -> 87 | D77: =C77/Ingresos!$D$68 -> 0.019478611
A78: Renta: gimnasio y centro deportivo | B78: Plaza Sakbé | C78: =Ingresos!$D$44 -> 81.30929 | D78: =C78/Ingresos!$D$68 -> 0.018204507
A79: Renta variable sobre ventas | B79: Plaza Sakbé | C79: =Ingresos!$D$47 -> 72.636299 | D79: =C79/Ingresos!$D$68 -> 0.016262693
A80: Estacionamiento en días de evento | B80: Estadio: gasto del público | C80: =Ingresos!$D$21 -> 69.152 | D80: =C80/Ingresos!$D$68 -> 0.015482585
A81: Renta: cines | B81: Plaza Sakbé | C81: =Ingresos!$D$43 -> 67.757742 | D81: =C81/Ingresos!$D$68 -> 0.015170422
A82: Renta por NFL / fútbol americano | B82: Estadio: eventos | C82: =Ingresos!$D$10 -> 60 | D82: =C82/Ingresos!$D$68 -> 0.013433525
A83: Fachada LED exterior | B83: Estadio: palcos y patrocinios | C83: =Ingresos!$D$29 -> 60 | D83: =C83/Ingresos!$D$68 -> 0.013433525
A84: Publicidad y patrocinio de la plaza | B84: Plaza Sakbé | C84: =Ingresos!$D$49 -> 60 | D84: =C84/Ingresos!$D$68 -> 0.013433525
A85: Congresos, convenciones y eventos privados | B85: Estadio: días sin evento | C85: =Ingresos!$D$34 -> 50 | D85: =C85/Ingresos!$D$68 -> 0.011194604
A86: Eventos en el parque de la azotea | B86: Plaza Sakbé | C86: =Ingresos!$D$50 -> 40 | D86: =C86/Ingresos!$D$68 -> 0.0089556834
A87: Tours y museo del deporte | B87: Estadio: días sin evento | C87: =Ingresos!$D$32 -> 37.5 | D87: =C87/Ingresos!$D$68 -> 0.0083959532
A88: Publicidad en pantallas y anillos LED | B88: Estadio: palcos y patrocinios | C88: =Ingresos!$D$28 -> 35 | D88: =C88/Ingresos!$D$68 -> 0.007836223
A89: Caminata sobre la cubierta | B89: Estadio: días sin evento | C89: =Ingresos!$D$33 -> 33 | D89: =C89/Ingresos!$D$68 -> 0.0073884388
A90: Renta por partidos de selección e internacionales | B90: Estadio: eventos | C90: =Ingresos!$D$8 -> 30.6 | D90: =C90/Ingresos!$D$68 -> 0.0068510978
A91: Mercancía (participación) | B91: Estadio: gasto del público | C91: =Ingresos!$D$19 -> 26.9424 | D91: =C91/Ingresos!$D$68 -> 0.0060321901
A92: Renta por eventos de arena (box, UFC, básquet, lucha) | B92: Estadio: eventos | C92: =Ingresos!$D$12 -> 24 | D92: =C92/Ingresos!$D$68 -> 0.00537341
A93: Renta por otros eventos (religiosos, corporativos, graduaciones, e-sports) | B93: Estadio: eventos | C93: =Ingresos!$D$13 -> 24 | D93: =C93/Ingresos!$D$68 -> 0.00537341
A94: Filmación, comerciales y fotos | B94: Estadio: días sin evento | C94: =Ingresos!$D$36 -> 20 | D94: =C94/Ingresos!$D$68 -> 0.0044778417
A95: Kioscos e islas temporales | B95: Plaza Sakbé | C95: =Ingresos!$D$48 -> 16.8 | D95: =C95/Ingresos!$D$68 -> 0.003761387
A96: Contenido digital, app y datos | B96: Estadio: días sin evento | C96: =Ingresos!$D$37 -> 15 | D96: =C96/Ingresos!$D$68 -> 0.0033583813
A97: Carga de autos eléctricos | B97: Energía y reciclaje | C97: =Ingresos!$D$55 -> 11.388 | D97: =C97/Ingresos!$D$68 -> 0.0025496831
A98: Renta de antenas y red | B98: Estadio: días sin evento | C98: =Ingresos!$D$38 -> 10 | D98: =C98/Ingresos!$D$68 -> 0.0022389208
A99: Renta de cancha y vestidores | B99: Estadio: días sin evento | C99: =Ingresos!$D$35 -> 9 | D99: =C99/Ingresos!$D$68 -> 0.0020150288
A100: Certificados de Energía Limpia | B100: Energía y reciclaje | C100: =Ingresos!$D$56 -> 4.7774248 | D100: =C100/Ingresos!$D$68 -> 0.0010696276
A101: Venta de reciclables | B101: Energía y reciclaje | C101: =Ingresos!$D$57 -> 2 | D101: =C101/Ingresos!$D$68 -> 0.00044778417
A102: Total | C102: =SUM(C61:C101) -> 4466.4375
A104: Cómo leerlo
A105: • El estadio solo no se paga con la operación en un plazo razonable; ningún estadio de este tamaño lo hace. Lo que lo hace viable es la Plaza Sakbé (rentas todos los días) y que el gobierno ponga la obra común.
A106: ="• Los paneles se recalcularon con pérdidas reales: la cubierta genera más de lo que gasta el estadio, pero todo el conjunto (sobre todo la plaza) consume "&TEXT(Energia!$D$31/Energia!$D$20,"0.0")&" veces lo que generan." -> • Los paneles se recalcularon con pérdidas reales: la cubierta genera más de lo que gasta el estadio, pero todo el conjunto (sobre todo la plaza) consume 3.7 veces lo que generan.
A107: • No incluye: terreno, financiamiento (intereses), inflación, ni la venta anticipada de palcos, que en México se ha usado para pagar parte de la obra (Estadio Azteca vendió palcos a 99 años).
...

Sheet Supuestos
A1: Supuestos del modelo (todo lo editable está aquí)
A2: Azul = dato editable. Negro = fórmula. Verde = liga a otra hoja. Pesos de 2026, sin inflación. Las tres columnas son tres escenarios: cambia cualquier número y todo el libro se recalcula.
A4: Concepto | B4: Unidad | C4: Conservador | D4: Base | E4: Optimista | F4: Nota / fuente
A6: Generales e inversión
A7: Tipo de cambio | B7: MXN/USD | C7: 18.5 | D7: 18.5 | E7: 18.5 | F7: Mismo supuesto que el presupuesto
A8: Inversión de construcción, sin IVA | B8: M MXN | C8: 53245 | D8: 53245 | E8: 53245 | F8: Presupuesto_Materiales_Yaxche_Sakbe.xlsx, total sin IVA (el IVA de obra se acredita). Sin terreno.
A9: Costo directo de obra | B9: M MXN | C9: 37235 | D9: 37235 | E9: 37235 | F9: Presupuesto: costo directo
A10: Parte del estadio (con indirectos) | B10: M MXN | C10: 17734 | D10: 17734 | E10: 17734 | F10: Presupuesto: indicadores
A11: Parte de la Plaza Sakbé (con indirectos) | B11: M MXN | C11: 17196 | D11: 17196 | E11: 17196 | F11: Presupuesto: indicadores
A12: Parte común: subterráneo, estacionamiento, explanada, redes | B12: M MXN | C12: 18316 | D12: 18316 | E12: 18316 | F12: Presupuesto: indicadores
A13: Gastos preoperativos y capital de trabajo | B13: M MXN | C13: 400 | D13: 300 | E13: 250 | F13: Contratación, marketing de apertura, pruebas, inventarios
A14: Avance de obra año 1 | B14: % | C14: 0.2 | D14: 0.2 | E14: 0.2 | F14: Obra de 4 años
A15: Avance de obra año 2 | B15: % | C15: 0.3 | D15: 0.3 | E15: 0.3
A16: Avance de obra año 3 | B16: % | C16: 0.3 | D16: 0.3 | E16: 0.3
A17: Avance de obra año 4 | B17: % | C17: 0.2 | D17: 0.2 | E17: 0.2
A18: Arranque: ingresos del año 1 de operación | B18: % del estable | C18: 0.8 | D18: 0.85 | E18: 0.9 | F18: Plaza a medio llenar y calendario de eventos incompleto
A19: Arranque: ingresos del año 2 de operación | B19: % del estable | C19: 0.9 | D19: 0.95 | E19: 1
A20: Tasa de descuento real | B20: % | C20: 0.09 | D20: 0.08 | E20: 0.07 | F20: Real (sin inflación). Equivale a ~12 % nominal con 4 % de inflación
A21: ISR | B21: % | C21: 0.3 | D21: 0.3 | E21: 0.3 | F21: Ley del ISR, personas morales
A22: Depreciación fiscal de construcciones | B22: %/año | C22: 0.05 | D22: 0.05 | E22: 0.05 | F22: LISR art. 34: 5 % anual (20 años)
A23: Esquema APP: fracción de la obra común que pone el gobierno | B23: % | C23: 1 | D23: 1 | E23: 1 | F23: Solo para el bloque "Base con APP" del flujo. Estacionamiento, explanada y redes son infraestructura pública
A25: Calendario de eventos del estadio
A26: Fútbol de liga (club local): eventos al año | B26: eventos | C26: 25 | D26: 30 | E26: 34
A27: Fútbol de liga (club local): asistencia promedio | B27: personas | C27: 45000 | D27: 58000 | E27: 70000
A28: Fútbol de liga (club local): boleto promedio | B28: MXN | C28: 380 | D28: 480 | E28: 600
A29: Fútbol de liga (club local): renta del estadio | B29: % de taquilla | C29: 0.1 | D29: 0.12 | E29: 0.15 | F29: Lo que el club / promotor paga al estadio
A30: Fútbol de liga (club local): gasto en alimentos y bebidas | B30: MXN/persona | C30: 150 | D30: 190 | E30: 240
A31: Selección nacional y partidos internacionales: eventos al año | B31: eventos | C31: 2 | D31: 3 | E31: 4
A32: Selección nacional y partidos internacionales: asistencia promedio | B32: personas | C32: 70000 | D32: 80000 | E32: 90000
A33: Selección nacional y partidos internacionales: boleto promedio | B33: MXN | C33: 700 | D33: 850 | E33: 1000
A34: Selección nacional y partidos internacionales: renta del estadio | B34: % de taquilla | C34: 0.12 | D34: 0.15 | E34: 0.18 | F34: Lo que el club / promotor paga al estadio
A35: Selección nacional y partidos internacionales: gasto en alimentos y bebidas | B35: MXN/persona | C35: 170 | D35: 210 | E35: 260
A36: Conciertos: eventos al año | B36: eventos | C36: 8 | D36: 12 | E36: 18 | F36: Un concierto al mes en el escenario base
A37: Conciertos: asistencia promedio | B37: personas | C37: 80000 | D37: 92000 | E37: 100000
A38: Conciertos: boleto promedio | B38: MXN | C38: 1700 | D38: 2200 | E38: 2600
A39: Conciertos: renta del estadio | B39: % de taquilla | C39: 0.08 | D39: 0.1 | E39: 0.12 | F39: Venue fee típico 8–12 % de la taquilla
A40: Conciertos: gasto en alimentos y bebidas | B40: MXN/persona | C40: 280 | D40: 350 | E40: 450
A41: NFL / fútbol americano: eventos al año | B41: eventos | C41: 0 | D41: 1 | E41: 1
A42: NFL / fútbol americano: asistencia promedio | B42: personas | C42: 70000 | D42: 78000 | E42: 85000
A43: NFL / fútbol americano: boleto promedio | B43: MXN | C43: 2500 | D43: 3200 | E43: 4000
A44: NFL / fútbol americano: renta fija del estadio | B44: M MXN/evento | C44: 45 | D44: 60 | E44: 80
A45: NFL / fútbol americano: gasto en alimentos y bebidas | B45: MXN/persona | C45: 300 | D45: 380 | E45: 480
A46: Festivales (días): eventos al año | B46: eventos | C46: 4 | D46: 6 | E46: 10
A47: Festivales (días): asistencia promedio | B47: personas | C47: 50000 | D47: 60000 | E47: 70000
A48: Festivales (días): boleto promedio | B48: MXN | C48: 1500 | D48: 1800 | E48: 2200
A49: Festivales (días): renta fija del estadio | B49: M MXN/evento | C49: 10 | D49: 15 | E49: 20
A50: Festivales (días): gasto en alimentos y bebidas | B50: MXN/persona | C50: 280 | D50: 350 | E50: 450
A51: Modo arena: box, UFC, básquet, lucha: eventos al año | B51: eventos | C51: 1 | D51: 2 | E51: 4
... A60: Otros: religiosos, corporativos, graduaciones, e-sports: gasto en alimentos y bebidas | B60: MXN/persona | C60: 120 | D60: 150 | E60: 200
A61: Aforo máximo | B61: lugares | C61: 100289 | D61: 100289 | E61: 100289 | F61: Medido en el modelo 3D
A62: Participación del estadio en alimentos y bebidas | B62: % de ventas | C62: 0.35 | D62: 0.4 | E62: 0.45 | F62: Contrato de concesión (el concesionario pone personal e insumos)
A63: Gasto en mercancía | B63: MXN/persona | C63: 40 | D63: 60 | E63: 80
A64: Participación del estadio en mercancía | B64: % de ventas | C64: 0.1 | D64: 0.12 | E64: 0.15
A65: Cuota de instalación por boleto (eventos que no son fútbol) | B65: MXN/boleto | C65: 40 | D65: 50 | E65: 70 | F65: Facility fee: se cobra dentro del boleto, va al estadio
A66: Comisión de boletaje que regresa al estadio | B66: % de taquilla | C66: 0.02 | D66: 0.03 | E66: 0.04 | F66: Rebate de la boletera por exclusividad (cargo por servicio compartido)
A67: Lugares de hospitalidad VIP por evento (no abonados) | B67: lugares | C67: 1500 | D67: 2000 | E67: 2500
A68: Precio del paquete VIP | B68: MXN/persona | C68: 2000 | D68: 2500 | E68: 3000
A69: Margen del estadio en VIP | B69: % | C69: 0.25 | D69: 0.3 | E69: 0.35
A70: Autos por asistente | B70: autos/persona | C70: 0.07 | D70: 0.08 | E70: 0.09 | F70: La mayoría llega en transporte público; tope = cajones
A71: Tarifa de estacionamiento en evento | B71: MXN/auto | C71: 200 | D71: 250 | E71: 300
A72: Personal por evento (seguridad, acomodadores, limpieza, médicos) | B72: personas | C72: 2800 | D72: 2500 | E72: 2200
A73: Costo del personal por evento | B73: MXN/persona | C73: 950 | D73: 900 | E73: 850
A75: Palcos, asientos club, patrocinios y publicidad
A76: Palcos | B76: palcos | C76: 200 | D76: 250 | E76: 280 | F76: Nivel entre grada media y alta
A77: Renta anual por palco | B77: M MXN | C77: 1.4 | D77: 1.8 | E77: 2.2 | F77: 12–16 lugares, todos los eventos
A78: Palcos rentados | B78: % | C78: 0.8 | D78: 0.9 | E78: 0.95
A79: Asientos club | B79: lugares | C79: 3000 | D79: 4000 | E79: 5000 | F79: Con salón, comida y estacionamiento
A80: Membresía anual por asiento club | B80: MXN | C80: 45000 | D80: 60000 | E80: 75000
A81: Asientos club vendidos | B81: % | C81: 0.75 | D81: 0.85 | E81: 0.95
A82: Derechos de nombre (naming rights) | B82: M USD/año | C82: 4 | D82: 6 | E82: 8 | F82: Estadios nuevos de 100k: USD 5–20 M/año
A83: Patrocinios oficiales y exclusividad de bebidas | B83: M MXN/año | C83: 100 | D83: 150 | E83: 200
A84: Publicidad en pantallas y anillos LED del estadio | B84: M MXN/año | C84: 20 | D84: 35 | E84: 50
A85: Fachada LED exterior (pauta publicitaria) | B85: M MXN/año | C85: 40 | D85: 60 | E85: 90 | F85: 383 m de fachada LED medidos en el modelo
A87: Ingresos en días sin evento
A88: Visitantes de tours y museo del deporte | B88: personas/año | C88: 100000 | D88: 150000 | E88: 220000
A89: Boleto de tour | B89: MXN | C89: 200 | D89: 250 | E89: 300
A90: Caminata sobre la cubierta (experiencia en el techo) | B90: personas/año | C90: 40000 | D90: 60000 | E90: 90000 | F90: Como el skywalk de Tottenham o el Up at The O2
A91: Boleto de la caminata | B91: MXN | C91: 450 | D91: 550 | E91: 650
A92: Congresos, convenciones y eventos privados en salones y palcos | B92: eventos/año | C92: 120 | D92: 200 | E92: 300
A93: Renta promedio por evento privado | B93: MXN | C93: 180000 | D93: 250000 | E93: 320000
A94: Renta de cancha y vestidores (corporativos, academias, visorias) | B94: rentas/año | C94: 40 | D94: 60 | E94: 80
A95: Renta por uso de cancha | B95: MXN | C95: 120000 | D95: 150000 | E95: 180000
A96: Filmación, comerciales y sesiones de fotos | B96: M MXN/año | C96: 10 | D96: 20 | E96: 30
A97: Contenido digital, app y datos | B97: M MXN/año | C97: 8 | D97: 15 | E97: 25
A98: Renta de antenas y red (5G, DAS, WiFi) | B98: M MXN/año | C98: 6 | D98: 10 | E98: 15
A99: Venta de reciclables (PET, aluminio, cartón) | B99: M MXN/año | C99: 1 | D99: 2 | E99: 3
A101: Plaza Sakbé
A102: Superficie construida de la plaza | B102: m² | C102: 386084 | D102: 386084 | E102: 386084 | F102: Medido en el modelo 3D
A103: Superficie rentable / construida | B103: % | C103: 0.62 | D103: 0.65 | E103: 0.68 | F103: El resto: pasillos, núcleos, sanitarios, cuartos de máquinas
A104: Tiendas: parte del área rentable | B104: % | C104: 0.3 | D104: 0.3 | E104: 0.3 | F104: Según el programa por nivel del modelo
A105: Tiendas: renta | B105: MXN/m²/mes | C105: 600 | D105: 750 | E105: 900 | F105: Rango de centros comerciales clase A en México
A106: Restaurantes y terrazas: parte del área rentable | B106: % | C106: 0.2 | D106: 0.2 | E106: 0.2 | F106: Según el programa por nivel del modelo
A107: Restaurantes y terrazas: renta | B107: MXN/m²/mes | C107: 450 | D107: 550 | E107: 650 | F107: Rango de centros comerciales clase A en México
A108: Cines: parte del área rentable | B108: % | C108: 0.1 | D108: 0.1 | E108: 0.1 | F108: Según el programa por nivel del modelo
A109: Cines: renta | B109: MXN/m²/mes | C109: 200 | D109: 250 | E109: 300 | F109: Rango de centros comerciales clase A en México
A110: Gimnasio y centro deportivo: parte del área rentable | B110: % | C110: 0.1 | D110: 0.1 | E110: 0.1 | F110: Según el programa por nivel del modelo
A111: Gimnasio y centro deportivo: renta | B111: MXN/m²/mes | C111: 250 | D111: 300 | E111: 350 | F111: Rango de centros comerciales clase A en México
A112: Clínica, guardería y museo: parte del área rentable | B112: % | C112: 0.1 | D112: 0.1 | E112: 0.1 | F112: Según el programa por nivel del modelo
A113: Clínica, guardería y museo: renta | B113: MXN/m²/mes | C113: 280 | D113: 350 | E113: 420 | F113: Rango de centros comerciales clase A en México
... A115: Oficinas y coworking: renta | B115: MXN/m²/mes | C115: 380 | D115: 450 | E115: 550 | F115: Rango de centros comerciales clase A en México
...

Sheet Eventos
A1: Calendario de eventos del estadio
A2: Cuántos eventos, cuánta gente y cuánto se vende en taquilla. Dinero en millones de MXN.
A4: Concepto | B4: Unidad | C4: Conservador | D4: Base | E4: Optimista | F4: Nota / fuente
A6: Fútbol de liga (club local)
A7: Eventos al año | B7: eventos | C7: =Supuestos!$C$26 -> 25 | D7: =Supuestos!$D$26 -> 30 | E7: =Supuestos!$E$26 -> 34
A8: Asistencia por evento | B8: personas | C8: =MIN(Supuestos!$C$27,Supuestos!$C$61) -> 45000 | D8: =MIN(Supuestos!$D$27,Supuestos!$D$61) -> 58000 | E8: =MIN(Supuestos!$E$27,Supuestos!$E$61) -> 70000 | F8: Tope = aforo
A9: Asistentes al año | B9: personas | C9: =Eventos!$C$7*Eventos!$C$8 -> 1125000 | D9: =Eventos!$D$7*Eventos!$D$8 -> 1740000 | E9: =Eventos!$E$7*Eventos!$E$8 -> 2380000
A10: Taquilla bruta | B10: M MXN | C10: =Eventos!$C$9*Supuestos!$C$28/10^6 -> 427.5 | D10: =Eventos!$D$9*Supuestos!$D$28/10^6 -> 835.2 | E10: =Eventos!$E$9*Supuestos!$E$28/10^6 -> 1428 | F10: Va al club o al promotor
A11: Ventas de alimentos y bebidas | B11: M MXN | C11: =Eventos!$C$9*Supuestos!$C$30/10^6 -> 168.75 | D11: =Eventos!$D$9*Supuestos!$D$30/10^6 -> 330.6 | E11: =Eventos!$E$9*Supuestos!$E$30/10^6 -> 571.2
A12: Autos por evento | B12: autos | C12: =MIN(Supuestos!$C$123,Eventos!$C$8*Supuestos!$C$70) -> 3150 | D12: =MIN(Supuestos!$D$123,Eventos!$D$8*Supuestos!$D$70) -> 4640 | E12: =MIN(Supuestos!$E$123,Eventos!$E$8*Supuestos!$E$70) -> 5688
A14: Selección nacional y partidos internacionales
A15: Eventos al año | B15: eventos | C15: =Supuestos!$C$31 -> 2 | D15: =Supuestos!$D$31 -> 3 | E15: =Supuestos!$E$31 -> 4
A16: Asistencia por evento | B16: personas | C16: =MIN(Supuestos!$C$32,Supuestos!$C$61) -> 70000 | D16: =MIN(Supuestos!$D$32,Supuestos!$D$61) -> 80000 | E16: =MIN(Supuestos!$E$32,Supuestos!$E$61) -> 90000 | F16: Tope = aforo
A17: Asistentes al año | B17: personas | C17: =Eventos!$C$15*Eventos!$C$16 -> 140000 | D17: =Eventos!$D$15*Eventos!$D$16 -> 240000 | E17: =Eventos!$E$15*Eventos!$E$16 -> 360000
A18: Taquilla bruta | B18: M MXN | C18: =Eventos!$C$17*Supuestos!$C$33/10^6 -> 98 | D18: =Eventos!$D$17*Supuestos!$D$33/10^6 -> 204 | E18: =Eventos!$E$17*Supuestos!$E$33/10^6 -> 360 | F18: Va al club o al promotor
A19: Ventas de alimentos y bebidas | B19: M MXN | C19: =Eventos!$C$17*Supuestos!$C$35/10^6 -> 23.8 | D19: =Eventos!$D$17*Supuestos!$D$35/10^6 -> 50.4 | E19: =Eventos!$E$17*Supuestos!$E$35/10^6 -> 93.6
A20: Autos por evento | B20: autos | C20: =MIN(Supuestos!$C$123,Eventos!$C$16*Supuestos!$C$70) -> 4900 | D20: =MIN(Supuestos!$D$123,Eventos!$D$16*Supuestos!$D$70) -> 5688 | E20: =MIN(Supuestos!$E$123,Eventos!$E$16*Supuestos!$E$70) -> 5688
A22: Conciertos
A23: Eventos al año | B23: eventos | C23: =Supuestos!$C$36 -> 8 | D23: =Supuestos!$D$36 -> 12 | E23: =Supuestos!$E$36 -> 18
A24: Asistencia por evento | B24: personas | C24: =MIN(Supuestos!$C$37,Supuestos!$C$61) -> 80000 | D24: =MIN(Supuestos!$D$37,Supuestos!$D$61) -> 92000 | E24: =MIN(Supuestos!$E$37,Supuestos!$E$61) -> 100000 | F24: Tope = aforo
A25: Asistentes al año | B25: personas | C25: =Eventos!$C$23*Eventos!$C$24 -> 640000 | D25: =Eventos!$D$23*Eventos!$D$24 -> 1104000 | E25: =Eventos!$E$23*Eventos!$E$24 -> 1800000
A26: Taquilla bruta | B26: M MXN | C26: =Eventos!$C$25*Supuestos!$C$38/10^6 -> 1088 | D26: =Eventos!$D$25*Supuestos!$D$38/10^6 -> 2428.8 | E26: =Eventos!$E$25*Supuestos!$E$38/10^6 -> 4680 | F26: Va al club o al promotor
A27: Ventas de alimentos y bebidas | B27: M MXN | C27: =Eventos!$C$25*Supuestos!$C$40/10^6 -> 179.2 | D27: =Eventos!$D$25*Supuestos!$D$40/10^6 -> 386.4 | E27: =Eventos!$E$25*Supuestos!$E$40/10^6 -> 810
A28: Autos por evento | B28: autos | C28: =MIN(Supuestos!$C$123,Eventos!$C$24*Supuestos!$C$70) -> 5600 | D28: =MIN(Supuestos!$D$123,Eventos!$D$24*Supuestos!$D$70) -> 5688 | E28: =MIN(Supuestos!$E$123,Eventos!$E$24*Supuestos!$E$70) -> 5688
A30: NFL / fútbol americano
A31: Eventos al año | B31: eventos | C31: =Supuestos!$C$41 -> 0 | D31: =Supuestos!$D$41 -> 1 | E31: =Supuestos!$E$41 -> 1
A32: Asistencia por evento | B32: personas | C32: =MIN(Supuestos!$C$42,Supuestos!$C$61) -> 70000 | D32: =MIN(Supuestos!$D$42,Supuestos!$D$61) -> 78000 | E32: =MIN(Supuestos!$E$42,Supuestos!$E$61) -> 85000 | F32: Tope = aforo
A33: Asistentes al año | B33: personas | C33: =Eventos!$C$31*Eventos!$C$32 -> 0 | D33: =Eventos!$D$31*Eventos!$D$32 -> 78000 | E33: =Eventos!$E$31*Eventos!$E$32 -> 85000
A34: Taquilla bruta | B34: M MXN | C34: =Eventos!$C$33*Supuestos!$C$43/10^6 -> 0 | D34: =Eventos!$D$33*Supuestos!$D$43/10^6 -> 249.6 | E34: =Eventos!$E$33*Supuestos!$E$43/10^6 -> 340 | F34: Va al club o al promotor
A35: Ventas de alimentos y bebidas | B35: M MXN | C35: =Eventos!$C$33*Supuestos!$C$45/10^6 -> 0 | D35: =Eventos!$D$33*Supuestos!$D$45/10^6 -> 29.64 | E35: =Eventos!$E$33*Supuestos!$E$45/10^6 -> 40.8
A36: Autos por evento | B36: autos | C36: =MIN(Supuestos!$C$123,Eventos!$C$32*Supuestos!$C$70) -> 4900 | D36: =MIN(Supuestos!$D$123,Eventos!$D$32*Supuestos!$D$70) -> 5688 | E36: =MIN(Supuestos!$E$123,Eventos!$E$32*Supuestos!$E$70) -> 5688
A38: Festivales (días)
A39: Eventos al año | B39: eventos | C39: =Supuestos!$C$46 -> 4 | D39: =Supuestos!$D$46 -> 6 | E39: =Supuestos!$E$46 -> 10
A40: Asistencia por evento | B40: personas | C40: =MIN(Supuestos!$C$47,Supuestos!$C$61) -> 50000 | D40: =MIN(Supuestos!$D$47,Supuestos!$D$61) -> 60000 | E40: =MIN(Supuestos!$E$47,Supuestos!$E$61) -> 70000 | F40: Tope = aforo
A41: Asistentes al año | B41: personas | C41: =Eventos!$C$39*Eventos!$C$40 -> 200000 | D41: =Eventos!$D$39*Eventos!$D$40 -> 360000 | E41: =Eventos!$E$39*Eventos!$E$40 -> 700000
A42: Taquilla bruta | B42: M MXN | C42: =Eventos!$C$41*Supuestos!$C$48/10^6 -> 300 | D42: =Eventos!$D$41*Supuestos!$D$48/10^6 -> 648 | E42: =Eventos!$E$41*Supuestos!$E$48/10^6 -> 1540 | F42: Va al club o al promotor
A43: Ventas de alimentos y bebidas | B43: M MXN | C43: =Eventos!$C$41*Supuestos!$C$50/10^6 -> 56 | D43: =Eventos!$D$41*Supuestos!$D$50/10^6 -> 126 | E43: =Eventos!$E$41*Supuestos!$E$50/10^6 -> 315
A44: Autos por evento | B44: autos | C44: =MIN(Supuestos!$C$123,Eventos!$C$40*Supuestos!$C$70) -> 3500 | D44: =MIN(Supuestos!$D$123,Eventos!$D$40*Supuestos!$D$70) -> 4800 | E44: =MIN(Supuestos!$E$123,Eventos!$E$40*Supuestos!$E$70) -> 5688
A46: Modo arena: box, UFC, básquet, lucha
A47: Eventos al año | B47: eventos | C47: =Supuestos!$C$51 -> 1 | D47: =Supuestos!$D$51 -> 2 | E47: =Supuestos!$E$51 -> 4
A48: Asistencia por evento | B48: personas | C48: =MIN(Supuestos!$C$52,Supuestos!$C$61) -> 40000 | D48: =MIN(Supuestos!$D$52,Supuestos!$D$61) -> 50000 | E48: =MIN(Supuestos!$E$52,Supuestos!$E$61) -> 60000 | F48: Tope = aforo
A49: Asistentes al año | B49: personas | C49: =Eventos!$C$47*Eventos!$C$48 -> 40000 | D49: =Eventos!$D$47*Eventos!$D$48 -> 100000 | E49: =Eventos!$E$47*Eventos!$E$48 -> 240000
A50: Taquilla bruta | B50: M MXN | C50: =Eventos!$C$49*Supuestos!$C$53/10^6 -> 48 | D50: =Eventos!$D$49*Supuestos!$D$53/10^6 -> 150 | E50: =Eventos!$E$49*Supuestos!$E$53/10^6 -> 480 | F50: Va al club o al promotor
A51: Ventas de alimentos y bebidas | B51: M MXN | C51: =Eventos!$C$49*Supuestos!$C$55/10^6 -> 8.8 | D51: =Eventos!$D$49*Supuestos!$D$55/10^6 -> 28 | E51: =Eventos!$E$49*Supuestos!$E$55/10^6 -> 84
A52: Autos por evento | B52: autos | C52: =MIN(Supuestos!$C$123,Eventos!$C$48*Supuestos!$C$70) -> 2800 | D52: =MIN(Supuestos!$D$123,Eventos!$D$48*Supuestos!$D$70) -> 4000 | E52: =MIN(Supuestos!$E$123,Eventos!$E$48*Supuestos!$E$70) -> 5400
A54: Otros: religiosos, corporativos, graduaciones, e-sports
A55: Eventos al año | B55: eventos | C55: =Supuestos!$C$56 -> 2 | D55: =Supuestos!$D$56 -> 4 | E55: =Supuestos!$E$56 -> 6
A56: Asistencia por evento | B56: personas | C56: =MIN(Supuestos!$C$57,Supuestos!$C$61) -> 25000 | D56: =MIN(Supuestos!$D$57,Supuestos!$D$61) -> 30000 | E56: =MIN(Supuestos!$E$57,Supuestos!$E$61) -> 40000 | F56: Tope = aforo
A57: Asistentes al año | B57: personas | C57: =Eventos!$C$55*Eventos!$C$56 -> 50000 | D57: =Eventos!$D$55*Eventos!$D$56 -> 120000 | E57: =Eventos!$E$55*Eventos!$E$56 -> 240000
A58: Taquilla bruta | B58: M MXN | C58: =Eventos!$C$57*Supuestos!$C$58/10^6 -> 15 | D58: =Eventos!$D$57*Supuestos!$D$58/10^6 -> 48 | E58: =Eventos!$E$57*Supuestos!$E$58/10^6 -> 120 | F58: Va al club o al promotor
A59: Ventas de alimentos y bebidas | B59: M MXN | C59: =Eventos!$C$57*Supuestos!$C$60/10^6 -> 6 | D59: =Eventos!$D$57*Supuestos!$D$60/10^6 -> 18 | E59: =Eventos!$E$57*Supuestos!$E$60/10^6 -> 48
A60: Autos por evento | B60: autos | C60: =MIN(Supuestos!$C$123,Eventos!$C$56*Supuestos!$C$70) -> 1750 | D60: =MIN(Supuestos!$D$123,Eventos!$D$56*Supuestos!$D$70) -> 2400 | E60: =MIN(Supuestos!$E$123,Eventos!$E$56*Supuestos!$E$70) -> 3600
A62: Totales
A63: Días de evento al año | B63: días | C63: =Eventos!$C$7+Eventos!$C$15+Eventos!$C$23+Eventos!$C$31+Eventos!$C$39+Eventos!$C$47+Eventos!$C$55 -> 42 | D63: =Eventos!$D$7+Eventos!$D$15+Eventos!$D$23+Eventos!$D$31+Eventos!$D$39+Eventos!$D$47+Eventos!$D$55 -> 58 | E63: =Eventos!$E$7+Eventos!$E$15+Eventos!$E$23+Eventos!$E$31+Eventos!$E$39+Eventos!$E$47+Eventos!$E$55 -> 77
A64: Asistentes al año | B64: personas | C64: =Eventos!$C$9+Eventos!$C$17+Eventos!$C$25+Eventos!$C$33+Eventos!$C$41+Eventos!$C$49+Eventos!$C$57 -> 2195000 | D64: =Eventos!$D$9+Eventos!$D$17+Eventos!$D$25+Eventos!$D$33+Eventos!$D$41+Eventos!$D$49+Eventos!$D$57 -> 3742000 | E64: =Eventos!$E$9+Eventos!$E$17+Eventos!$E$25+Eventos!$E$33+Eventos!$E$41+Eventos!$E$49+Eventos!$E$57 -> 5805000
A65: Asistentes a eventos que no son fútbol | B65: personas | C65: =Eventos!$C$64-Eventos!$C$9-Eventos!$C$17 -> 930000 | D65: =Eventos!$D$64-Eventos!$D$9-Eventos!$D$17 -> 1762000 | E65: =Eventos!$E$64-Eventos!$E$9-Eventos!$E$17 -> 3065000
A66: Taquilla bruta total | B66: M MXN | C66: =Eventos!$C$10+Eventos!$C$18+Eventos!$C$26+Eventos!$C$34+Eventos!$C$42+Eventos!$C$50+Eventos!$C$58 -> 1976.5 | D66: =Eventos!$D$10+Eventos!$D$18+Eventos!$D$26+Eventos!$D$34+Eventos!$D$42+Eventos!$D$50+Eventos!$D$58 -> 4563.6 | E66: =Eventos!$E$10+Eventos!$E$18+Eventos!$E$26+Eventos!$E$34+Eventos!$E$42+Eventos!$E$50+Eventos!$E$58 -> 8948
A67: Ventas de alimentos y bebidas | B67: M MXN | C67: =Eventos!$C$11+Eventos!$C$19+Eventos!$C$27+Eventos!$C$35+Eventos!$C$43+Eventos!$C$51+Eventos!$C$59 -> 442.55 | D67: =Eventos!$D$11+Eventos!$D$19+Eventos!$D$27+Eventos!$D$35+Eventos!$D$43+Eventos!$D$51+Eventos!$D$59 -> 969.04 | E67: =Eventos!$E$11+Eventos!$E$19+Eventos!$E$27+Eventos!$E$35+Eventos!$E$43+Eventos!$E$51+Eventos!$E$59 -> 1962.6
A68: Ventas de mercancía | B68: M MXN | C68: =Eventos!$C$64*Supuestos!$C$63/10^6 -> 87.8 | D68: =Eventos!$D$64*Supuestos!$D$63/10^6 -> 224.52 | E68: =Eventos!$E$64*Supuestos!$E$63/10^6 -> 464.4
A69: Autos en días de evento | B69: autos/año | C69: =Eventos!$C$7*Eventos!$C$12+Eventos!$C$15*Eventos!$C$20+Eventos!$C$23*Eventos!$C$28+Eventos!$C$31*Eventos!$C$36+Eventos!$C$39*Eventos!$C$44+Eventos!$C$47*Eventos!$C$52+Eventos!$C$55*Eventos!$C$60 -> 153650 | D69: =Eventos!$D$7*Eventos!$D$12+Eventos!$D$15*Eventos!$D$20+Eventos!$D$23*Eventos!$D$28+Eventos!$D$31*Eventos!$D$36+Eventos!$D$39*Eventos!$D$44+Eventos!$D$47*Eventos!$D$52+Eventos!$D$55*Eventos!$D$60 -> 276608 | E69: =Eventos!$E$7*Eventos!$E$12+Eventos!$E$15*Eventos!$E$20+Eventos!$E$23*Eventos!$E$28+Eventos!$E$31*Eventos!$E$36+Eventos!$E$39*Eventos!$E$44+Eventos!$E$47*Eventos!$E$52+Eventos!$E$55*Eventos!$E$60 -> 424296
A70: Días sin evento | B70: días | C70: =365-Eventos!$C$63 -> 323 | D70: =365-Eventos!$D$63 -> 307 | E70: =365-Eventos!$E$63 -> 288

Sheet Energia
A1: Energía: cuánto generan los paneles, cuánto se consume y cuánto se paga
A2: GWh = millones de kWh. Dinero en millones de MXN. Los paneles se recalcularon con pérdidas reales (la cifra anterior de 16 GWh solo en la cubierta era optimista).
A4: Concepto | B4: Unidad | C4: Conservador | D4: Base | E4: Optimista | F4: Nota / fuente
A6: 1. Rendimiento de los paneles
A7: Sol que llega (radiación horizontal) | B7: kWh/m²/año | C7: =Supuestos!$C$132 -> 1850 | D7: =Supuestos!$D$132 -> 1900 | E7: =Supuestos!$E$132 -> 2000
A8: Lo que sobrevive a las pérdidas | B8: % | C8: =(1-Supuestos!$C$133)*(1-Supuestos!$C$134)*(1-Supuestos!$C$135)*(1-Supuestos!$C$136)*(1-Supuestos!$C$137)*(1-Supuestos!$C$138)*(1-Supuestos!$C$139) -> 0.72950044 | D8: =(1-Supuestos!$D$133)*(1-Supuestos!$D$134)*(1-Supuestos!$D$135)*(1-Supuestos!$D$136)*(1-Supuestos!$D$137)*(1-Supuestos!$D$138)*(1-Supuestos!$D$139) -> 0.76936863 | E8: =(1-Supuestos!$E$133)*(1-Supuestos!$E$134)*(1-Supuestos!$E$135)*(1-Supuestos!$E$136)*(1-Supuestos!$E$137)*(1-Supuestos!$E$138)*(1-Supuestos!$E$139) -> 0.81913267 | F8: Producto de las 7 pérdidas de Supuestos
A9: Rendimiento en cubierta y pérgolas | B9: kWh/kWp/año | C9: =Energia!$C$7*Energia!$C$8 -> 1349.5758 | D9: =Energia!$D$7*Energia!$D$8 -> 1461.8004 | E9: =Energia!$E$7*Energia!$E$8 -> 1638.2653
A10: Rendimiento del vidrio fotovoltaico vertical | B10: kWh/kWp/año | C10: =Energia!$C$9*Supuestos!$C$145 -> 485.84729 | D10: =Energia!$D$9*Supuestos!$D$145 -> 555.48415 | E10: =Energia!$E$9*Supuestos!$E$145 -> 655.30614
A12: 2. Generación solar
A13: Potencia en la cubierta del estadio | B13: kWp | C13: =Supuestos!$C$140*Supuestos!$C$143 -> 8172.41 | D13: =Supuestos!$D$140*Supuestos!$D$143 -> 8653.14 | E13: =Supuestos!$E$140*Supuestos!$E$143 -> 9133.87
A14: Potencia en pérgolas de la azotea | B14: kWp | C14: =Supuestos!$C$141*Supuestos!$C$143 -> 833 | D14: =Supuestos!$D$141*Supuestos!$D$143 -> 882 | E14: =Supuestos!$E$141*Supuestos!$E$143 -> 931
A15: Potencia en la fachada (vidrio fotovoltaico) | B15: kWp | C15: =Supuestos!$C$142*Supuestos!$C$144 -> 3575.76 | D15: =Supuestos!$D$142*Supuestos!$D$144 -> 3575.76 | E15: =Supuestos!$E$142*Supuestos!$E$144 -> 3575.76
A16: Potencia total | B16: kWp | C16: =Energia!$C$13+Energia!$C$14+Energia!$C$15 -> 12581.17 | D16: =Energia!$D$13+Energia!$D$14+Energia!$D$15 -> 13110.9 | E16: =Energia!$E$13+Energia!$E$14+Energia!$E$15 -> 13640.63
A17: Generación de la cubierta del estadio | B17: GWh/año | C17: =Energia!$C$13*Energia!$C$9/10^6 -> 11.029287 | D17: =Energia!$D$13*Energia!$D$9/10^6 -> 12.649163 | E17: =Energia!$E$13*Energia!$E$9/10^6 -> 14.963703
A18: Generación de las pérgolas | B18: GWh/año | C18: =Energia!$C$14*Energia!$C$9/10^6 -> 1.1241966 | D18: =Energia!$D$14*Energia!$D$9/10^6 -> 1.2893079 | E18: =Energia!$E$14*Energia!$E$9/10^6 -> 1.525225
A19: Generación de la fachada | B19: GWh/año | C19: =Energia!$C$15*Energia!$C$10/10^6 -> 1.7372733 | D19: =Energia!$D$15*Energia!$D$10/10^6 -> 1.986278 | E19: =Energia!$E$15*Energia!$E$10/10^6 -> 2.3432175
A20: Generación solar total | B20: GWh/año | C20: =Energia!$C$17+Energia!$C$18+Energia!$C$19 -> 13.890757 | D20: =Energia!$D$17+Energia!$D$18+Energia!$D$19 -> 15.924749 | E20: =Energia!$E$17+Energia!$E$18+Energia!$E$19 -> 18.832145
A21: Lo que darían sin ninguna pérdida | B21: GWh/año | C21: =(Energia!$C$13+Energia!$C$14)*Energia!$C$7/10^6+Energia!$C$15*Energia!$C$7*Supuestos!$C$145/10^6 -> 19.041465 | D21: =(Energia!$D$13+Energia!$D$14)*Energia!$D$7/10^6+Energia!$D$15*Energia!$D$7*Supuestos!$D$145/10^6 -> 20.698465 | E21: =(Energia!$E$13+Energia!$E$14)*Energia!$E$7/10^6+Energia!$E$15*Energia!$E$7*Supuestos!$E$145/10^6 -> 22.990348 | F21: Potencia × sol, sin pérdidas
A22: Energía solar que se pierde (calor, polvo, sombra, inversores, cables) | B22: GWh/año | C22: =Energia!$C$21-Energia!$C$20 -> 5.1507079 | D22: =Energia!$D$21-Energia!$D$20 -> 4.7737154 | E22: =Energia!$E$21-Energia!$E$20 -> 4.1582029
A23: Pérdida por degradación al año 10 | B23: GWh/año | C23: =Energia!$C$20*(1-(1-Supuestos!$C$146)^9) -> 0.61272714 | D23: =Energia!$D$20*(1-(1-Supuestos!$D$146)^9) -> 0.70244741 | E23: =Energia!$E$20*(1-(1-Supuestos!$E$146)^9) -> 0.83069386
A24: Generación en el año 30 | B24: GWh/año | C24: =Energia!$C$20*(1-Supuestos!$C$146)^29 -> 12.011445 | D24: =Energia!$D$20*(1-Supuestos!$D$146)^29 -> 13.770254 | E24: =Energia!$E$20*(1-Supuestos!$E$146)^29 -> 16.284301
A26: 3. Consumo
A27: Estadio | B27: GWh/año | C27: =(Supuestos!$C$147*8760/1000+Supuestos!$C$148*Eventos!$C$63)/1000 -> 8.652 | D27: =(Supuestos!$D$147*8760/1000+Supuestos!$D$148*Eventos!$D$63)/1000 -> 8.594 | E27: =(Supuestos!$E$147*8760/1000+Supuestos!$E$148*Eventos!$E$63)/1000 -> 8.721
A28: Plaza Sakbé (locales y áreas comunes) | B28: GWh/año | C28: =Supuestos!$C$102*Supuestos!$C$149/10^6 -> 52.12134 | D28: =Supuestos!$D$102*Supuestos!$D$149/10^6 -> 44.39966 | E28: =Supuestos!$E$102*Supuestos!$E$149/10^6 -> 38.6084
A29: Estacionamiento subterráneo | B29: GWh/año | C29: =Supuestos!$C$151*Supuestos!$C$150/10^6 -> 4.188324 | D29: =Supuestos!$D$151*Supuestos!$D$150/10^6 -> 3.839297 | E29: =Supuestos!$E$151*Supuestos!$E$150/10^6 -> 3.49027
A30: Carga de autos eléctricos | B30: GWh/año | C30: =Supuestos!$C$127*Supuestos!$C$128*365/10^6 -> 1.022 | D30: =Supuestos!$D$127*Supuestos!$D$128*365/10^6 -> 1.752 | E30: =Supuestos!$E$127*Supuestos!$E$128*365/10^6 -> 2.628
A31: Consumo total del conjunto | B31: GWh/año | C31: =Energia!$C$27+Energia!$C$28+Energia!$C$29+Energia!$C$30 -> 65.983664 | D31: =Energia!$D$27+Energia!$D$28+Energia!$D$29+Energia!$D$30 -> 58.584957 | E31: =Energia!$E$27+Energia!$E$28+Energia!$E$29+Energia!$E$30 -> 53.44767
A33: 4. Balance de todo el conjunto
A34: Parte del consumo que cubren los paneles | B34: % | C34: =Energia!$C$20/Energia!$C$31 -> 0.21051812 | D34: =Energia!$D$20/Energia!$D$31 -> 0.27182318 | E34: =Energia!$E$20/Energia!$E$31 -> 0.35234735
A35: Paneles vs. consumo del estadio solo | B35: % | C35: =Energia!$C$17/Energia!$C$27 -> 1.2747673 | D35: =Energia!$D$17/Energia!$D$27 -> 1.4718598 | E35: =Energia!$E$17/Energia!$E$27 -> 1.7158242 | F35: La cubierta sola genera más de lo que gasta el estadio
A36: Energía que hay que comprar a la red | B36: GWh/año | C36: =MAX(0,Energia!$C$31-Energia!$C$20) -> 52.092907 | D36: =MAX(0,Energia!$D$31-Energia!$D$20) -> 42.660208 | E36: =MAX(0,Energia!$E$31-Energia!$E$20) -> 34.615525
A37: Costo de la energía comprada (todo el conjunto) | B37: M MXN/año | C37: =Energia!$C$36*Supuestos!$C$153 -> 161.48801 | D37: =Energia!$D$36*Supuestos!$D$153 -> 119.44858 | E37: =Energia!$E$36*Supuestos!$E$153 -> 86.538812
A38: Lo que costaría toda la energía sin paneles | B38: M MXN/año | C38: =Energia!$C$31*Supuestos!$C$153 -> 204.54936 | D38: =Energia!$D$31*Supuestos!$D$153 -> 164.03788 | E38: =Energia!$E$31*Supuestos!$E$153 -> 133.61918
A40: 5. Quién paga qué
A41: Consumo que pagan los locatarios (su medidor) | B41: GWh/año | C41: =Energia!$C$28*Supuestos!$C$152 -> 33.878871 | D41: =Energia!$D$28*Supuestos!$D$152 -> 28.859779 | E41: =Energia!$E$28*Supuestos!$E$152 -> 25.09546
A42: Consumo que paga el dueño | B42: GWh/año | C42: =Energia!$C$31-Energia!$C$41 -> 32.104793 | D42: =Energia!$D$31-Energia!$D$41 -> 29.725178 | E42: =Energia!$E$31-Energia!$E$41 -> 28.35221 | F42: Estadio + áreas comunes + estacionamiento + cargadores
A43: Energía que compra el dueño | B43: GWh/año | C43: =MAX(0,Energia!$C$42-Energia!$C$20) -> 18.214036 | D43: =MAX(0,Energia!$D$42-Energia!$D$20) -> 13.800429 | E43: =MAX(0,Energia!$E$42-Energia!$E$20) -> 9.5200649
A44: Costo de energía del dueño | B44: M MXN/año | C44: =Energia!$C$43*Supuestos!$C$153 -> 56.463512 | D44: =Energia!$D$43*Supuestos!$D$153 -> 38.6412 | E44: =Energia!$E$43*Supuestos!$E$153 -> 23.800162
A45: Costo de energía de los locatarios | B45: M MXN/año | C45: =Energia!$C$41*Supuestos!$C$153 -> 105.0245 | D45: =Energia!$D$41*Supuestos!$D$153 -> 80.807381 | E45: =Energia!$E$41*Supuestos!$E$153 -> 62.73865 | F45: Lo pagan ellos
A47: 6. Lo que valen los paneles
A48: Ahorro por energía solar | B48: M MXN/año | C48: =Energia!$C$20*Supuestos!$C$153 -> 43.061346 | D48: =Energia!$D$20*Supuestos!$D$153 -> 44.589298 | E48: =Energia!$E$20*Supuestos!$E$153 -> 47.080363 | F48: Toda la energía solar se usa en el sitio (el conjunto siempre consume más)
A49: Certificados de Energía Limpia | B49: M MXN/año | C49: =Energia!$C$20*1000*Supuestos!$C$154/10^6 -> 2.7781514 | D49: =Energia!$D$20*1000*Supuestos!$D$154/10^6 -> 4.7774248 | E49: =Energia!$E$20*1000*Supuestos!$E$154/10^6 -> 7.532858
A50: Operación y limpieza de los paneles | B50: M MXN/año | C50: =Energia!$C$16*Supuestos!$C$162/10^6 -> 3.774351 | D50: =Energia!$D$16*Supuestos!$D$162/10^6 -> 3.277725 | E50: =Energia!$E$16*Supuestos!$E$162/10^6 -> 2.728126
A51: CO₂ evitado | B51: t/año | C51: =Energia!$C$20*1000*Supuestos!$C$155 -> 6084.1515 | D51: =Energia!$D$20*1000*Supuestos!$D$155 -> 6975.0402 | E51: =Energia!$E$20*1000*Supuestos!$E$155 -> 8248.4796
A52: Factor de indirectos y contingencia | B52: x | C52: =Supuestos!$C$8/Supuestos!$C$9 -> 1.4299718 | D52: =Supuestos!$D$8/Supuestos!$D$9 -> 1.4299718 | E52: =Supuestos!$E$8/Supuestos!$E$9 -> 1.4299718 | F52: Total sin IVA / costo directo
A53: Inversión: paneles de la cubierta del estadio | B53: M MXN | C53: =(Supuestos!$C$140*Supuestos!$C$156+Energia!$C$13*Supuestos!$C$157)*Energia!$C$52/10^6 -> 475.28934 | D53: =(Supuestos!$D$140*Supuestos!$D$156+Energia!$D$13*Supuestos!$D$157)*Energia!$D$52/10^6 -> 478.17655 | E53: =(Supuestos!$E$140*Supuestos!$E$156+Energia!$E$13*Supuestos!$E$157)*Energia!$E$52/10^6 -> 481.06375
A54: Inversión: pérgolas solares | B54: M MXN | C54: =Energia!$C$14*Supuestos!$C$158*Energia!$C$52/10^6 -> 19.654247 | D54: =Energia!$D$14*Supuestos!$D$158*Energia!$D$52/10^6 -> 20.81038 | E54: =Energia!$E$14*Supuestos!$E$158*Energia!$E$52/10^6 -> 21.966512
A55: Inversión: sobrecosto del vidrio fotovoltaico | B55: M MXN | C55: =(Supuestos!$C$142*Supuestos!$C$159+Energia!$C$15*Supuestos!$C$160)*Energia!$C$52/10^6 -> 324.86093 | D55: =(Supuestos!$D$142*Supuestos!$D$159+Energia!$D$15*Supuestos!$D$160)*Energia!$D$52/10^6 -> 324.86093 | E55: =(Supuestos!$E$142*Supuestos!$E$159+Energia!$E$15*Supuestos!$E$160)*Energia!$E$52/10^6 -> 324.86093
A56: Inversión solar total | B56: M MXN | C56: =Energia!$C$53+Energia!$C$54+Energia!$C$55 -> 819.80451 | D56: =Energia!$D$53+Energia!$D$54+Energia!$D$55 -> 823.84785 | E56: =Energia!$E$53+Energia!$E$54+Energia!$E$55 -> 827.89119
A57: Recuperación: solo la cubierta del estadio | B57: años | C57: =Energia!$C$53/((Energia!$C$17*Supuestos!$C$153)+Energia!$C$17*1000*Supuestos!$C$154/10^6-Energia!$C$13*Supuestos!$C$162/10^6) -> 14.00178 | D57: =Energia!$D$53/((Energia!$D$17*Supuestos!$D$153)+Energia!$D$17*1000*Supuestos!$D$154/10^6-Energia!$D$13*Supuestos!$D$162/10^6) -> 12.906556 | E57: =Energia!$E$53/((Energia!$E$17*Supuestos!$E$153)+Energia!$E$17*1000*Supuestos!$E$154/10^6-Energia!$E$13*Supuestos!$E$162/10^6) -> 11.572945
A58: Recuperación: pérgolas de la azotea | B58: años | C58: =Energia!$C$54/((Energia!$C$18*Supuestos!$C$153)+Energia!$C$18*1000*Supuestos!$C$154/10^6-Energia!$C$14*Supuestos!$C$162/10^6) -> 5.6805022 | D58: =Energia!$D$54/((Energia!$D$18*Supuestos!$D$153)+Energia!$D$18*1000*Supuestos!$D$154/10^6-Energia!$D$14*Supuestos!$D$162/10^6) -> 5.5107059 | E58: =Energia!$E$54/((Energia!$E$18*Supuestos!$E$153)+Energia!$E$18*1000*Supuestos!$E$154/10^6-Energia!$E$14*Supuestos!$E$162/10^6) -> 5.1845073
A59: Recuperación: vidrio fotovoltaico de la fachada | B59: años | C59: =Energia!$C$55/((Energia!$C$19*Supuestos!$C$153)+Energia!$C$19*1000*Supuestos!$C$154/10^6-Energia!$C$15*Supuestos!$C$162/10^6) -> 69.708548 | D59: =Energia!$D$55/((Energia!$D$19*Supuestos!$D$153)+Energia!$D$19*1000*Supuestos!$D$154/10^6-Energia!$D$15*Supuestos!$D$162/10^6) -> 61.719309 | E59: =Energia!$E$55/((Energia!$E$19*Supuestos!$E$153)+Energia!$E$19*1000*Supuestos!$E$154/10^6-Energia!$E$15*Supuestos!$E$162/10^6) -> 53.429503 | F59: No se paga solo: se justifica por imagen y certificación, o se cambia por vidrio normal
A60: Comparación: esa misma cubierta en ETFE costaría | B60: M MXN | C60: =Supuestos!$C$140*Supuestos!$C$161*Energia!$C$52/10^6 -> 1065.517 | D60: =Supuestos!$D$140*Supuestos!$D$161*Energia!$D$52/10^6 -> 1065.517 | E60: =Supuestos!$E$140*Supuestos!$E$161*Energia!$E$52/10^6 -> 1065.517 | F60: Los paneles salen más baratos que la cubierta de ETFE que reemplazan
A61: Recuperación: todo el sistema solar | B61: años | C61: =Energia!$C$56/(Energia!$C$48+Energia!$C$49-Energia!$C$50) -> 19.488926 | D61: =Energia!$D$56/(Energia!$D$48+Energia!$D$49-Energia!$D$50) -> 17.875152 | E61: =Energia!$E$56/(Energia!$E$48+Energia!$E$49-Energia!$E$50) -> 15.956243

Sheet Agua
A1: Agua: consumo, lluvia, reúso y costo
A2: m³ por año. Dinero en millones de MXN.
A4: Concepto | B4: Unidad | C4: Conservador | D4: Base | E4: Optimista | F4: Nota / fuente
A6: Consumo
A7: Estadio | B7: m³/año | C7: =Supuestos!$C$165*Eventos!$C$63+Supuestos!$C$166 -> 78400 | D7: =Supuestos!$D$165*Eventos!$D$63+Supuestos!$D$166 -> 91800 | E7: =Supuestos!$E$165*Eventos!$E$63+Supuestos!$E$166 -> 105000
A8: Plaza Sakbé | B8: m³/año | C8: =Supuestos!$C$102*Supuestos!$C$167 -> 231650.4 | D8: =Supuestos!$D$102*Supuestos!$D$167 -> 212346.2 | E8: =Supuestos!$E$102*Supuestos!$E$167 -> 193042
A9: Riego del parque y jardines | B9: m³/año | C9: =Supuestos!$C$168*Supuestos!$C$169 -> 30769.75 | D9: =Supuestos!$D$168*Supuestos!$D$169 -> 28531.95 | E9: =Supuestos!$E$168*Supuestos!$E$169 -> 25175.25
A10: Consumo total | B10: m³/año | C10: =Agua!$C$7+Agua!$C$8+Agua!$C$9 -> 340820.15 | D10: =Agua!$D$7+Agua!$D$8+Agua!$D$9 -> 332678.15 | E10: =Agua!$E$7+Agua!$E$8+Agua!$E$9 -> 323217.25
A12: De dónde sale
A13: Lluvia captada | B13: m³/año | C13: =Supuestos!$C$170*Supuestos!$C$171*Supuestos!$C$172 -> 46984.8 | D13: =Supuestos!$D$170*Supuestos!$D$171*Supuestos!$D$172 -> 54815.6 | E13: =Supuestos!$E$170*Supuestos!$E$171*Supuestos!$E$172 -> 62646.4 | F13: Cisternas de 7,700 m³ en el sótano
A14: Agua gris tratada y reusada | B14: m³/año | C14: =(Agua!$C$7+Agua!$C$8)*Supuestos!$C$173 -> 93015.12 | D14: =(Agua!$D$7+Agua!$D$8)*Supuestos!$D$173 -> 121658.48 | E14: =(Agua!$E$7+Agua!$E$8)*Supuestos!$E$173 -> 149021
A15: Agua comprada a la red | B15: m³/año | C15: =MAX(0,Agua!$C$10-Agua!$C$13-Agua!$C$14) -> 200820.23 | D15: =MAX(0,Agua!$D$10-Agua!$D$13-Agua!$D$14) -> 156204.07 | E15: =MAX(0,Agua!$E$10-Agua!$E$13-Agua!$E$14) -> 111549.85
A16: Parte que no viene de la red | B16: % | C16: =1-Agua!$C$15/Agua!$C$10 -> 0.4107736 | D16: =1-Agua!$D$15/Agua!$D$10 -> 0.5304649 | E16: =1-Agua!$E$15/Agua!$E$10 -> 0.65487656
A18: Costo
A19: Agua comprada | B19: M MXN/año | C19: =Agua!$C$15*Supuestos!$C$174/10^6 -> 11.045113 | D19: =Agua!$D$15*Supuestos!$D$174/10^6 -> 7.0291831 | E19: =Agua!$E$15*Supuestos!$E$174/10^6 -> 3.9042448
A20: Tratamiento del agua reusada | B20: M MXN/año | C20: =Agua!$C$14*Supuestos!$C$175/10^6 -> 1.1161814 | D20: =Agua!$D$14*Supuestos!$D$175/10^6 -> 1.2165848 | E20: =Agua!$E$14*Supuestos!$E$175/10^6 -> 1.192168
A21: Costo total del agua | B21: M MXN/año | C21: =Agua!$C$19+Agua!$C$20 -> 12.161294 | D21: =Agua!$D$19+Agua!$D$20 -> 8.2457679 | E21: =Agua!$E$19+Agua!$E$20 -> 5.0964127 | F21: El dueño la paga y la recupera en parte con la cuota de mantenimiento
A22: Ahorro por lluvia y reúso | B22: M MXN/año | C22: =(Agua!$C$13+Agua!$C$14)*Supuestos!$C$174/10^6-Agua!$C$20 -> 6.5838142 | D22: =(Agua!$D$13+Agua!$D$14)*Supuestos!$D$174/10^6-Agua!$D$20 -> 6.7247488 | E22: =(Agua!$E$13+Agua!$E$14)*Supuestos!$E$174/10^6-Agua!$E$20 -> 6.216191

Sheet Ingresos
A1: Todas las fuentes de ingreso (año estable de operación)
A2: Millones de MXN por año. Lo que entra al dueño del estadio y la plaza (no la taquilla completa del promotor).
A4: Concepto | B4: Unidad | C4: Conservador | D4: Base | E4: Optimista | F4: Nota / fuente
A6: A. Estadio: eventos
A7: Renta por partidos de fútbol de liga | B7: M MXN/año | C7: =Eventos!$C$10*Supuestos!$C$29 -> 42.75 | D7: =Eventos!$D$10*Supuestos!$D$29 -> 100.224 | E7: =Eventos!$E$10*Supuestos!$E$29 -> 214.2 | F7: % de taquilla
A8: Renta por partidos de selección e internacionales | B8: M MXN/año | C8: =Eventos!$C$18*Supuestos!$C$34 -> 11.76 | D8: =Eventos!$D$18*Supuestos!$D$34 -> 30.6 | E8: =Eventos!$E$18*Supuestos!$E$34 -> 64.8 | F8: % de taquilla
A9: Renta por conciertos | B9: M MXN/año | C9: =Eventos!$C$26*Supuestos!$C$39 -> 87.04 | D9: =Eventos!$D$26*Supuestos!$D$39 -> 242.88 | E9: =Eventos!$E$26*Supuestos!$E$39 -> 561.6 | F9: % de taquilla (venue fee)
A10: Renta por NFL / fútbol americano | B10: M MXN/año | C10: =Eventos!$C$31*Supuestos!$C$44 -> 0 | D10: =Eventos!$D$31*Supuestos!$D$44 -> 60 | E10: =Eventos!$E$31*Supuestos!$E$44 -> 80
A11: Renta por festivales | B11: M MXN/año | C11: =Eventos!$C$39*Supuestos!$C$49 -> 40 | D11: =Eventos!$D$39*Supuestos!$D$49 -> 90 | E11: =Eventos!$E$39*Supuestos!$E$49 -> 200
A12: Renta por eventos de arena (box, UFC, básquet, lucha) | B12: M MXN/año | C12: =Eventos!$C$47*Supuestos!$C$54 -> 8 | D12: =Eventos!$D$47*Supuestos!$D$54 -> 24 | E12: =Eventos!$E$47*Supuestos!$E$54 -> 72
A13: Renta por otros eventos (religiosos, corporativos, graduaciones, e-sports) | B13: M MXN/año | C13: =Eventos!$C$55*Supuestos!$C$59 -> 8 | D13: =Eventos!$D$55*Supuestos!$D$59 -> 24 | E13: =Eventos!$E$55*Supuestos!$E$59 -> 48
A14: Cuota de instalación por boleto | B14: M MXN/año | C14: =Eventos!$C$65*Supuestos!$C$65/10^6 -> 37.2 | D14: =Eventos!$D$65*Supuestos!$D$65/10^6 -> 88.1 | E14: =Eventos!$E$65*Supuestos!$E$65/10^6 -> 214.55 | F14: Todos los eventos menos fútbol
A15: Comisión de boletaje (rebate) | B15: M MXN/año | C15: =Eventos!$C$66*Supuestos!$C$66 -> 39.53 | D15: =Eventos!$D$66*Supuestos!$D$66 -> 136.908 | E15: =Eventos!$E$66*Supuestos!$E$66 -> 357.92
A17: B. Estadio: lo que gasta el público
A18: Alimentos y bebidas (participación de la concesión) | B18: M MXN/año | C18: =Eventos!$C$67*Supuestos!$C$62 -> 154.8925 | D18: =Eventos!$D$67*Supuestos!$D$62 -> 387.616 | E18: =Eventos!$E$67*Supuestos!$E$62 -> 883.17
A19: Mercancía (participación) | B19: M MXN/año | C19: =Eventos!$C$68*Supuestos!$C$64 -> 8.78 | D19: =Eventos!$D$68*Supuestos!$D$64 -> 26.9424 | E19: =Eventos!$E$68*Supuestos!$E$64 -> 69.66
A20: Paquetes VIP y hospitalidad por evento | B20: M MXN/año | C20: =Supuestos!$C$67*Eventos!$C$63*Supuestos!$C$68*Supuestos!$C$69/10^6 -> 31.5 | D20: =Supuestos!$D$67*Eventos!$D$63*Supuestos!$D$68*Supuestos!$D$69/10^6 -> 87 | E20: =Supuestos!$E$67*Eventos!$E$63*Supuestos!$E$68*Supuestos!$E$69/10^6 -> 202.125
A21: Estacionamiento en días de evento | B21: M MXN/año | C21: =Eventos!$C$69*Supuestos!$C$71/10^6 -> 30.73 | D21: =Eventos!$D$69*Supuestos!$D$71/10^6 -> 69.152 | E21: =Eventos!$E$69*Supuestos!$E$71/10^6 -> 127.2888
A23: C. Estadio: palcos, patrocinios y publicidad
A24: Palcos (renta anual) | B24: M MXN/año | C24: =Supuestos!$C$76*Supuestos!$C$77*Supuestos!$C$78 -> 224 | D24: =Supuestos!$D$76*Supuestos!$D$77*Supuestos!$D$78 -> 405 | E24: =Supuestos!$E$76*Supuestos!$E$77*Supuestos!$E$78 -> 585.2
A25: Asientos club (membresía anual) | B25: M MXN/año | C25: =Supuestos!$C$79*Supuestos!$C$80*Supuestos!$C$81/10^6 -> 101.25 | D25: =Supuestos!$D$79*Supuestos!$D$80*Supuestos!$D$81/10^6 -> 204 | E25: =Supuestos!$E$79*Supuestos!$E$80*Supuestos!$E$81/10^6 -> 356.25
A26: Derechos de nombre del estadio | B26: M MXN/año | C26: =Supuestos!$C$82*Supuestos!$C$7 -> 74 | D26: =Supuestos!$D$82*Supuestos!$D$7 -> 111 | E26: =Supuestos!$E$82*Supuestos!$E$7 -> 148
A27: Patrocinios oficiales y exclusividad de bebidas | B27: M MXN/año | C27: =Supuestos!$C$83 -> 100 | D27: =Supuestos!$D$83 -> 150 | E27: =Supuestos!$E$83 -> 200
A28: Publicidad en pantallas y anillos LED | B28: M MXN/año | C28: =Supuestos!$C$84 -> 20 | D28: =Supuestos!$D$84 -> 35 | E28: =Supuestos!$E$84 -> 50
A29: Fachada LED exterior | B29: M MXN/año | C29: =Supuestos!$C$85 -> 40 | D29: =Supuestos!$D$85 -> 60 | E29: =Supuestos!$E$85 -> 90
A31: D. Estadio: días sin evento
A32: Tours y museo del deporte | B32: M MXN/año | C32: =Supuestos!$C$88*Supuestos!$C$89/10^6 -> 20 | D32: =Supuestos!$D$88*Supuestos!$D$89/10^6 -> 37.5 | E32: =Supuestos!$E$88*Supuestos!$E$89/10^6 -> 66
A33: Caminata sobre la cubierta | B33: M MXN/año | C33: =Supuestos!$C$90*Supuestos!$C$91/10^6 -> 18 | D33: =Supuestos!$D$90*Supuestos!$D$91/10^6 -> 33 | E33: =Supuestos!$E$90*Supuestos!$E$91/10^6 -> 58.5
A34: Congresos, convenciones y eventos privados | B34: M MXN/año | C34: =Supuestos!$C$92*Supuestos!$C$93/10^6 -> 21.6 | D34: =Supuestos!$D$92*Supuestos!$D$93/10^6 -> 50 | E34: =Supuestos!$E$92*Supuestos!$E$93/10^6 -> 96
A35: Renta de cancha y vestidores | B35: M MXN/año | C35: =Supuestos!$C$94*Supuestos!$C$95/10^6 -> 4.8 | D35: =Supuestos!$D$94*Supuestos!$D$95/10^6 -> 9 | E35: =Supuestos!$E$94*Supuestos!$E$95/10^6 -> 14.4
A36: Filmación, comerciales y fotos | B36: M MXN/año | C36: =Supuestos!$C$96 -> 10 | D36: =Supuestos!$D$96 -> 20 | E36: =Supuestos!$E$96 -> 30
A37: Contenido digital, app y datos | B37: M MXN/año | C37: =Supuestos!$C$97 -> 8 | D37: =Supuestos!$D$97 -> 15 | E37: =Supuestos!$E$97 -> 25
A38: Renta de antenas y red | B38: M MXN/año | C38: =Supuestos!$C$98 -> 6 | D38: =Supuestos!$D$98 -> 10 | E38: =Supuestos!$E$98 -> 15
A40: E. Plaza Sakbé
A41: Renta: tiendas | B41: M MXN/año | C41: =Supuestos!$C$102*Supuestos!$C$103*Supuestos!$C$104*Supuestos!$C$105*12*Supuestos!$C$116/10^6 -> 423.97583 | D41: =Supuestos!$D$102*Supuestos!$D$103*Supuestos!$D$104*Supuestos!$D$105*12*Supuestos!$D$116/10^6 -> 609.81968 | E41: =Supuestos!$E$102*Supuestos!$E$103*Supuestos!$E$104*Supuestos!$E$105*12*Supuestos!$E$116/10^6 -> 808.08926
A42: Renta: restaurantes y terrazas | B42: M MXN/año | C42: =Supuestos!$C$102*Supuestos!$C$103*Supuestos!$C$106*Supuestos!$C$107*12*Supuestos!$C$116/10^6 -> 211.98791 | D42: =Supuestos!$D$102*Supuestos!$D$103*Supuestos!$D$106*Supuestos!$D$107*12*Supuestos!$D$116/10^6 -> 298.13406 | E42: =Supuestos!$E$102*Supuestos!$E$103*Supuestos!$E$106*Supuestos!$E$107*12*Supuestos!$E$116/10^6 -> 389.08001
A43: Renta: cines | B43: M MXN/año | C43: =Supuestos!$C$102*Supuestos!$C$103*Supuestos!$C$108*Supuestos!$C$109*12*Supuestos!$C$116/10^6 -> 47.108425 | D43: =Supuestos!$D$102*Supuestos!$D$103*Supuestos!$D$108*Supuestos!$D$109*12*Supuestos!$D$116/10^6 -> 67.757742 | E43: =Supuestos!$E$102*Supuestos!$E$103*Supuestos!$E$108*Supuestos!$E$109*12*Supuestos!$E$116/10^6 -> 89.787695
A44: Renta: gimnasio y centro deportivo | B44: M MXN/año | C44: =Supuestos!$C$102*Supuestos!$C$103*Supuestos!$C$110*Supuestos!$C$111*12*Supuestos!$C$116/10^6 -> 58.885532 | D44: =Supuestos!$D$102*Supuestos!$D$103*Supuestos!$D$110*Supuestos!$D$111*12*Supuestos!$D$116/10^6 -> 81.30929 | E44: =Supuestos!$E$102*Supuestos!$E$103*Supuestos!$E$110*Supuestos!$E$111*12*Supuestos!$E$116/10^6 -> 104.75231
A45: Renta: clínica, guardería y museo | B45: M MXN/año | C45: =Supuestos!$C$102*Supuestos!$C$103*Supuestos!$C$112*Supuestos!$C$113*12*Supuestos!$C$116/10^6 -> 65.951795 | D45: =Supuestos!$D$102*Supuestos!$D$103*Supuestos!$D$112*Supuestos!$D$113*12*Supuestos!$D$116/10^6 -> 94.860839 | E45: =Supuestos!$E$102*Supuestos!$E$103*Supuestos!$E$112*Supuestos!$E$113*12*Supuestos!$E$116/10^6 -> 125.70277
A46: Renta: oficinas y coworking | B46: M MXN/año | C46: =Supuestos!$C$102*Supuestos!$C$103*Supuestos!$C$114*Supuestos!$C$115*12*Supuestos!$C$116/10^6 -> 179.01202 | D46: =Supuestos!$D$102*Supuestos!$D$103*Supuestos!$D$114*Supuestos!$D$115*12*Supuestos!$D$116/10^6 -> 243.92787 | E46: =Supuestos!$E$102*Supuestos!$E$103*Supuestos!$E$114*Supuestos!$E$115*12*Supuestos!$E$116/10^6 -> 329.22155
A47: Renta variable sobre ventas | B47: M MXN/año | C47: =(Ingresos!$C$41+Ingresos!$C$42)*Supuestos!$C$117 -> 31.798187 | D47: =(Ingresos!$D$41+Ingresos!$D$42)*Supuestos!$D$117 -> 72.636299 | E47: =(Ingresos!$E$41+Ingresos!$E$42)*Supuestos!$E$117 -> 119.71693
A48: Kioscos e islas temporales | B48: M MXN/año | C48: =Supuestos!$C$118*Supuestos!$C$119*12/10^6 -> 10.8 | D48: =Supuestos!$D$118*Supuestos!$D$119*12/10^6 -> 16.8 | E48: =Supuestos!$E$118*Supuestos!$E$119*12/10^6 -> 24
A49: Publicidad y patrocinio de la plaza | B49: M MXN/año | C49: =Supuestos!$C$120 -> 40 | D49: =Supuestos!$D$120 -> 60 | E49: =Supuestos!$E$120 -> 90
A50: Eventos en el parque de la azotea | B50: M MXN/año | C50: =Supuestos!$C$121 -> 25 | D50: =Supuestos!$D$121 -> 40 | E50: =Supuestos!$E$121 -> 60
A51: Estacionamiento diario (sin evento) | B51: M MXN/año | C51: =Supuestos!$C$123*Supuestos!$C$124*Supuestos!$C$125*Supuestos!$C$126*Eventos!$C$70/10^6 -> 69.447067 | D51: =Supuestos!$D$123*Supuestos!$D$124*Supuestos!$D$125*Supuestos!$D$126*Eventos!$D$70/10^6 -> 125.72755 | E51: =Supuestos!$E$123*Supuestos!$E$124*Supuestos!$E$125*Supuestos!$E$126*Eventos!$E$70/10^6 -> 216.23501
A52: Cuota de mantenimiento de locatarios (CAM) | B52: M MXN/año | C52: =Supuestos!$C$102*Supuestos!$C$103*Supuestos!$C$116*Supuestos!$C$122*12/10^6 -> 176.6566 | D52: =Supuestos!$D$102*Supuestos!$D$103*Supuestos!$D$116*Supuestos!$D$122*12/10^6 -> 230.37632 | E52: =Supuestos!$E$102*Supuestos!$E$103*Supuestos!$E$116*Supuestos!$E$122*12/10^6 -> 284.3277 | F52: Paga la operación de áreas comunes
A54: F. Energía y reciclaje
A55: Carga de autos eléctricos | B55: M MXN/año | C55: =Supuestos!$C$127*Supuestos!$C$128*365*Supuestos!$C$129/10^6 -> 6.132 | D55: =Supuestos!$D$127*Supuestos!$D$128*365*Supuestos!$D$129/10^6 -> 11.388 | E55: =Supuestos!$E$127*Supuestos!$E$128*365*Supuestos!$E$129/10^6 -> 18.396
A56: Certificados de Energía Limpia | B56: M MXN/año | C56: =Energia!$C$49 -> 2.7781514 | D56: =Energia!$D$49 -> 4.7774248 | E56: =Energia!$E$49 -> 7.532858
A57: Venta de reciclables | B57: M MXN/año | C57: =Supuestos!$C$99 -> 1 | D57: =Supuestos!$D$99 -> 2 | E57: =Supuestos!$E$99 -> 3
A59: Totales
A60: Estadio: eventos | B60: M MXN/año | C60: =Ingresos!$C$7+Ingresos!$C$8+Ingresos!$C$9+Ingresos!$C$10+Ingresos!$C$11+Ingresos!$C$12+Ingresos!$C$13+Ingresos!$C$14+Ingresos!$C$15 -> 274.28 | D60: =Ingresos!$D$7+Ingresos!$D$8+Ingresos!$D$9+Ingresos!$D$10+Ingresos!$D$11+Ingresos!$D$12+Ingresos!$D$13+Ingresos!$D$14+Ingresos!$D$15 -> 796.712 | E60: =Ingresos!$E$7+Ingresos!$E$8+Ingresos!$E$9+Ingresos!$E$10+Ingresos!$E$11+Ingresos!$E$12+Ingresos!$E$13+Ingresos!$E$14+Ingresos!$E$15 -> 1813.07
A61: Estadio: gasto del público | B61: M MXN/año | C61: =Ingresos!$C$18+Ingresos!$C$19+Ingresos!$C$20+Ingresos!$C$21 -> 225.9025 | D61: =Ingresos!$D$18+Ingresos!$D$19+Ingresos!$D$20+Ingresos!$D$21 -> 570.7104 | E61: =Ingresos!$E$18+Ingresos!$E$19+Ingresos!$E$20+Ingresos!$E$21 -> 1282.2438
A62: Estadio: palcos y patrocinios | B62: M MXN/año | C62: =Ingresos!$C$24+Ingresos!$C$25+Ingresos!$C$26+Ingresos!$C$27+Ingresos!$C$28+Ingresos!$C$29 -> 559.25 | D62: =Ingresos!$D$24+Ingresos!$D$25+Ingresos!$D$26+Ingresos!$D$27+Ingresos!$D$28+Ingresos!$D$29 -> 965 | E62: =Ingresos!$E$24+Ingresos!$E$25+Ingresos!$E$26+Ingresos!$E$27+Ingresos!$E$28+Ingresos!$E$29 -> 1429.45
A63: Estadio: días sin evento | B63: M MXN/año | C63: =Ingresos!$C$32+Ingresos!$C$33+Ingresos!$C$34+Ingresos!$C$35+Ingresos!$C$36+Ingresos!$C$37+Ingresos!$C$38 -> 88.4 | D63: =Ingresos!$D$32+Ingresos!$D$33+Ingresos!$D$34+Ingresos!$D$35+Ingresos!$D$36+Ingresos!$D$37+Ingresos!$D$38 -> 174.5 | E63: =Ingresos!$E$32+Ingresos!$E$33+Ingresos!$E$34+Ingresos!$E$35+Ingresos!$E$36+Ingresos!$E$37+Ingresos!$E$38 -> 304.9
A64: Plaza Sakbé | B64: M MXN/año | C64: =Ingresos!$C$41+Ingresos!$C$42+Ingresos!$C$43+Ingresos!$C$44+Ingresos!$C$45+Ingresos!$C$46+Ingresos!$C$47+Ingresos!$C$48+Ingresos!$C$49+Ingresos!$C$50+Ingresos!$C$51+Ingresos!$C$52 -> 1340.6234 | D64: =Ingresos!$D$41+Ingresos!$D$42+Ingresos!$D$43+Ingresos!$D$44+Ingresos!$D$45+Ingresos!$D$46+Ingresos!$D$47+Ingresos!$D$48+Ingresos!$D$49+Ingresos!$D$50+Ingresos!$D$51+Ingresos!$D$52 -> 1941.3497 | E64: =Ingresos!$E$41+Ingresos!$E$42+Ingresos!$E$43+Ingresos!$E$44+Ingresos!$E$45+Ingresos!$E$46+Ingresos!$E$47+Ingresos!$E$48+Ingresos!$E$49+Ingresos!$E$50+Ingresos!$E$51+Ingresos!$E$52 -> 2640.9132
A65: Energía y reciclaje | B65: M MXN/año | C65: =Ingresos!$C$55+Ingresos!$C$56+Ingresos!$C$57 -> 9.9101514 | D65: =Ingresos!$D$55+Ingresos!$D$56+Ingresos!$D$57 -> 18.165425 | E65: =Ingresos!$E$55+Ingresos!$E$56+Ingresos!$E$57 -> 28.928858
A66: Total estadio (A a D) | B66: M MXN/año | C66: =Ingresos!$C$60+Ingresos!$C$61+Ingresos!$C$62+Ingresos!$C$63 -> 1147.8325 | D66: =Ingresos!$D$60+Ingresos!$D$61+Ingresos!$D$62+Ingresos!$D$63 -> 2506.9224 | E66: =Ingresos!$E$60+Ingresos!$E$61+Ingresos!$E$62+Ingresos!$E$63 -> 4829.6638
A67: Total Plaza Sakbé (E) | B67: M MXN/año | C67: =Ingresos!$C$64 -> 1340.6234 | D67: =Ingresos!$D$64 -> 1941.3497 | E67: =Ingresos!$E$64 -> 2640.9132
A68: INGRESOS TOTALES | B68: M MXN/año | C68: =Ingresos!$C$66+Ingresos!$C$67+Ingresos!$C$65 -> 2498.366 | D68: =Ingresos!$D$66+Ingresos!$D$67+Ingresos!$D$65 -> 4466.4375 | E68: =Ingresos!$E$66+Ingresos!$E$67+Ingresos!$E$65 -> 7499.5059
A69: Ingresos totales en dólares | B69: M USD/año | C69: =Ingresos!$C$68/Supuestos!$C$7 -> 135.04681 | D69: =Ingresos!$D$68/Supuestos!$D$7 -> 241.42905 | E69: =Ingresos!$E$68/Supuestos!$E$7 -> 405.3787
A70: Fuentes de ingreso contadas | B70: fuentes | C70: =41 -> 41 | D70: =41 -> 41 | E70: =41 -> 41
A71: Aparte: ahorro por paneles solares (ya está restado en el costo de energía) | B71: M MXN/año | C71: =Energia!$C$48 -> 43.061346 | D71: =Energia!$D$48 -> 44.589298 | E71: =Energia!$E$48 -> 47.080363
A73: Lo que deja cada concierto extra
A74: Renta y cuota de instalación | B74: M MXN | C74: =Supuestos!$C$37*Supuestos!$C$38*Supuestos!$C$39/10^6+Supuestos!$C$37*Supuestos!$C$65/10^6 -> 14.08 | D74: =Supuestos!$D$37*Supuestos!$D$38*Supuestos!$D$39/10^6+Supuestos!$D$37*Supuestos!$D$65/10^6 -> 24.84 | E74: =Supuestos!$E$37*Supuestos!$E$38*Supuestos!$E$39/10^6+Supuestos!$E$37*Supuestos!$E$65/10^6 -> 38.2
A75: Comisión de boletaje | B75: M MXN | C75: =Supuestos!$C$37*Supuestos!$C$38*Supuestos!$C$66/10^6 -> 2.72 | D75: =Supuestos!$D$37*Supuestos!$D$38*Supuestos!$D$66/10^6 -> 6.072 | E75: =Supuestos!$E$37*Supuestos!$E$38*Supuestos!$E$66/10^6 -> 10.4
A76: Alimentos, mercancía y VIP | B76: M MXN | C76: =Supuestos!$C$37*(Supuestos!$C$40*Supuestos!$C$62+Supuestos!$C$63*Supuestos!$C$64)/10^6+Supuestos!$C$67*Supuestos!$C$68*Supuestos!$C$69/10^6 -> 8.91 | D76: =Supuestos!$D$37*(Supuestos!$D$40*Supuestos!$D$62+Supuestos!$D$63*Supuestos!$D$64)/10^6+Supuestos!$D$67*Supuestos!$D$68*Supuestos!$D$69/10^6 -> 15.0424 | E76: =Supuestos!$E$37*(Supuestos!$E$40*Supuestos!$E$62+Supuestos!$E$63*Supuestos!$E$64)/10^6+Supuestos!$E$67*Supuestos!$E$68*Supuestos!$E$69/10^6 -> 24.075
A77: Estacionamiento | B77: M MXN | C77: =MIN(Supuestos!$C$123,Supuestos!$C$37*Supuestos!$C$70)*Supuestos!$C$71/10^6 -> 1.12 | D77: =MIN(Supuestos!$D$123,Supuestos!$D$37*Supuestos!$D$70)*Supuestos!$D$71/10^6 -> 1.422 | E77: =MIN(Supuestos!$E$123,Supuestos!$E$37*Supuestos!$E$70)*Supuestos!$E$71/10^6 -> 1.7064
A78: Menos: personal, energía y agua del evento | B78: M MXN | C78: =-(Supuestos!$C$72*Supuestos!$C$73/10^6+Supuestos!$C$148*1000*Supuestos!$C$153/10^6+Supuestos!$C$165*Supuestos!$C$174/10^6) -> -2.912 | D78: =-(Supuestos!$D$72*Supuestos!$D$73/10^6+Supuestos!$D$148*1000*Supuestos!$D$153/10^6+Supuestos!$D$165*Supuestos!$D$174/10^6) -> -2.4395 | E78: =-(Supuestos!$E$72*Supuestos!$E$73/10^6+Supuestos!$E$148*1000*Supuestos!$E$153/10^6+Supuestos!$E$165*Supuestos!$E$174/10^6) -> -2.0175
A79: Ganancia neta por concierto extra | B79: M MXN | C79: =Ingresos!$C$74+Ingresos!$C$75+Ingresos!$C$76+Ingresos!$C$77+Ingresos!$C$78 -> 23.918 | D79: =Ingresos!$D$74+Ingresos!$D$75+Ingresos!$D$76+Ingresos!$D$77+Ingresos!$D$78 -> 44.9369 | E79: =Ingresos!$E$74+Ingresos!$E$75+Ingresos!$E$76+Ingresos!$E$77+Ingresos!$E$78 -> 72.3639

Sheet Costos_Operacion
A1: Costos de operación (año estable)
A2: Millones de MXN por año.
A4: Concepto | B4: Unidad | C4: Conservador | D4: Base | E4: Optimista | F4: Nota / fuente
A6: Personal
A7: Personal permanente (estadio y corporativo) | B7: M MXN/año | C7: =Supuestos!$C$178*Supuestos!$C$179/10^6 -> 99 | D7: =Supuestos!$D$178*Supuestos!$D$179/10^6 -> 75.6 | E7: =Supuestos!$E$178*Supuestos!$E$179/10^6 -> 68
A8: Personal por evento | B8: M MXN/año | C8: =Supuestos!$C$72*Supuestos!$C$73*Eventos!$C$63/10^6 -> 111.72 | D8: =Supuestos!$D$72*Supuestos!$D$73*Eventos!$D$63/10^6 -> 130.5 | E8: =Supuestos!$E$72*Supuestos!$E$73*Eventos!$E$63/10^6 -> 143.99
A10: Energía y agua
A11: Energía comprada a la red (parte del dueño) | B11: M MXN/año | C11: =Energia!$C$44 -> 56.463512 | D11: =Energia!$D$44 -> 38.6412 | E11: =Energia!$E$44 -> 23.800162 | F11: Ya descuenta los paneles solares
A12: Operación y limpieza de paneles | B12: M MXN/año | C12: =Energia!$C$50 -> 3.774351 | D12: =Energia!$D$50 -> 3.277725 | E12: =Energia!$E$50 -> 2.728126
A13: Agua (comprada + tratamiento) | B13: M MXN/año | C13: =Agua!$C$21 -> 12.161294 | D13: =Agua!$D$21 -> 8.2457679 | E13: =Agua!$E$21 -> 5.0964127
A15: Mantenimiento
A16: Mantenimiento del edificio y sus sistemas | B16: M MXN/año | C16: =Supuestos!$C$9*Supuestos!$C$180 -> 446.82 | D16: =Supuestos!$D$9*Supuestos!$D$180 -> 372.35 | E16: =Supuestos!$E$9*Supuestos!$E$180 -> 335.115
A17: Contratos de escaleras eléctricas | B17: M MXN/año | C17: =Supuestos!$C$181*Supuestos!$C$182/10^6 -> 25.76 | D17: =Supuestos!$D$181*Supuestos!$D$182/10^6 -> 22.08 | E17: =Supuestos!$E$181*Supuestos!$E$182/10^6 -> 18.4
A18: Contratos de elevadores | B18: M MXN/año | C18: =Supuestos!$C$183*Supuestos!$C$184/10^6 -> 18.54 | D18: =Supuestos!$D$183*Supuestos!$D$184/10^6 -> 16.48 | E18: =Supuestos!$E$183*Supuestos!$E$184/10^6 -> 14.42
A19: Techo retráctil | B19: M MXN/año | C19: =Supuestos!$C$185 -> 20 | D19: =Supuestos!$D$185 -> 15 | E19: =Supuestos!$E$185 -> 12
A20: Cancha | B20: M MXN/año | C20: =Supuestos!$C$186 -> 30 | D20: =Supuestos!$D$186 -> 25 | E20: =Supuestos!$E$186 -> 20
A21: Jardinería y árboles | B21: M MXN/año | C21: =Supuestos!$C$187 -> 18 | D21: =Supuestos!$D$187 -> 15 | E21: =Supuestos!$E$187 -> 12
A22: Reserva para reposiciones mayores | B22: M MXN/año | C22: =Supuestos!$C$9*Supuestos!$C$198 -> 223.41 | D22: =Supuestos!$D$9*Supuestos!$D$198 -> 186.175 | E22: =Supuestos!$E$9*Supuestos!$E$198 -> 148.94
A24: Servicios
A25: Seguridad permanente 24/7 | B25: M MXN/año | C25: =Supuestos!$C$188 -> 55 | D25: =Supuestos!$D$188 -> 45 | E25: =Supuestos!$E$188 -> 40
A26: Limpieza permanente | B26: M MXN/año | C26: =Supuestos!$C$189 -> 30 | D26: =Supuestos!$D$189 -> 25 | E26: =Supuestos!$E$189 -> 22
A27: Recolección de residuos | B27: M MXN/año | C27: =Supuestos!$C$190 -> 12 | D27: =Supuestos!$D$190 -> 10 | E27: =Supuestos!$E$190 -> 8
A28: Telecomunicaciones, WiFi y sistemas | B28: M MXN/año | C28: =Supuestos!$C$191 -> 15 | D28: =Supuestos!$D$191 -> 12 | E28: =Supuestos!$E$191 -> 10
A29: Operación del estacionamiento | B29: M MXN/año | C29: =(Ingresos!$C$21+Ingresos!$C$51)*Supuestos!$C$197 -> 25.044267 | D29: =(Ingresos!$D$21+Ingresos!$D$51)*Supuestos!$D$197 -> 38.97591 | E29: =(Ingresos!$E$21+Ingresos!$E$51)*Supuestos!$E$197 -> 51.528571
A30: Operación de áreas comunes de la plaza (limpieza, seguridad, parque) | B30: M MXN/año | C30: =Ingresos!$C$52 -> 176.6566 | D30: =Ingresos!$D$52 -> 230.37632 | E30: =Ingresos!$E$52 -> 284.3277 | F30: Igual a la cuota de mantenimiento que pagan los locatarios
A32: Administración, seguros e impuestos locales
A33: Administración, marketing y ventas | B33: M MXN/año | C33: =Supuestos!$C$194 -> 150 | D33: =Supuestos!$D$194 -> 120 | E33: =Supuestos!$E$194 -> 100
A34: Comisiones por venta de patrocinios, naming y palcos | B34: M MXN/año | C34: =(Ingresos!$C$26+Ingresos!$C$27+Ingresos!$C$24+Ingresos!$C$25)*Supuestos!$C$195 -> 59.91 | D34: =(Ingresos!$D$26+Ingresos!$D$27+Ingresos!$D$24+Ingresos!$D$25)*Supuestos!$D$195 -> 87 | E34: =(Ingresos!$E$26+Ingresos!$E$27+Ingresos!$E$24+Ingresos!$E$25)*Supuestos!$E$195 -> 103.156
A35: Comisión y promoción de la plaza | B35: M MXN/año | C35: =Ingresos!$C$64*Supuestos!$C$196 -> 53.624934 | D35: =Ingresos!$D$64*Supuestos!$D$196 -> 58.24049 | E35: =Ingresos!$E$64*Supuestos!$E$196 -> 66.022831
A36: Seguros | B36: M MXN/año | C36: =Supuestos!$C$8*Supuestos!$C$192 -> 95.841 | D36: =Supuestos!$D$8*Supuestos!$D$192 -> 79.8675 | E36: =Supuestos!$E$8*Supuestos!$E$192 -> 63.894
A37: Predial | B37: M MXN/año | C37: =Supuestos!$C$8*Supuestos!$C$193 -> 53.245 | D37: =Supuestos!$D$8*Supuestos!$D$193 -> 53.245 | E37: =Supuestos!$E$8*Supuestos!$E$193 -> 42.596
A39: Totales
A40: Subtotal | B40: M MXN/año | C40: =Costos_Operacion!$C$7+Costos_Operacion!$C$8+Costos_Operacion!$C$11+Costos_Operacion!$C$12+Costos_Operacion!$C$13+Costos_Operacion!$C$16+Costos_Operacion!$C$17+Costos_Operacion!$C$18+Costos_Operacion!$C$19+Costos_Operacion!$C$20+Costos_Operacion!$C$21+Costos_Operacion!$C$22+Costos_Operacion!$C$25+Costos_Operacion!$C$26+Costos_Operacion!$C$27+Costos_Operacion!$C$28+Costos_Operacion!$C$29+Costos_Operacion!$C$30+Costos_Operacion!$C$33+Costos_Operacion!$C$34+Costos_Operacion!$C$35+Costos_Operacion!$C$36+Costos_Operacion!$C$37 -> 1791.971 | D40: =Costos_Operacion!$D$7+Costos_Operacion!$D$8+Costos_Operacion!$D$11+Costos_Operacion!$D$12+Costos_Operacion!$D$13+Costos_Operacion!$D$16+Costos_Operacion!$D$17+Costos_Operacion!$D$18+Costos_Operacion!$D$19+Costos_Operacion!$D$20+Costos_Operacion!$D$21+Costos_Operacion!$D$22+Costos_Operacion!$D$25+Costos_Operacion!$D$26+Costos_Operacion!$D$27+Costos_Operacion!$D$28+Costos_Operacion!$D$29+Costos_Operacion!$D$30+Costos_Operacion!$D$33+Costos_Operacion!$D$34+Costos_Operacion!$D$35+Costos_Operacion!$D$36+Costos_Operacion!$D$37 -> 1668.0549 | E40: =Costos_Operacion!$E$7+Costos_Operacion!$E$8+Costos_Operacion!$E$11+Costos_Operacion!$E$12+Costos_Operacion!$E$13+Costos_Operacion!$E$16+Costos_Operacion!$E$17+Costos_Operacion!$E$18+Costos_Operacion!$E$19+Costos_Operacion!$E$20+Costos_Operacion!$E$21+Costos_Operacion!$E$22+Costos_Operacion!$E$25+Costos_Operacion!$E$26+Costos_Operacion!$E$27+Costos_Operacion!$E$28+Costos_Operacion!$E$29+Costos_Operacion!$E$30+Costos_Operacion!$E$33+Costos_Operacion!$E$34+Costos_Operacion!$E$35+Costos_Operacion!$E$36+Costos_Operacion!$E$37 -> 1596.0148
A41: Imprevistos | B41: M MXN/año | C41: =Costos_Operacion!$C$40*Supuestos!$C$199 -> 89.598548 | D41: =Costos_Operacion!$D$40*Supuestos!$D$199 -> 50.041647 | E41: =Costos_Operacion!$E$40*Supuestos!$E$199 -> 31.920296
A42: COSTOS DE OPERACIÓN TOTALES | B42: M MXN/año | C42: =Costos_Operacion!$C$40+Costos_Operacion!$C$41 -> 1881.5695 | D42: =Costos_Operacion!$D$40+Costos_Operacion!$D$41 -> 1718.0966 | E42: =Costos_Operacion!$E$40+Costos_Operacion!$E$41 -> 1627.9351
A44: Resultado de operación
A45: Ingresos totales | B45: M MXN/año | C45: =Ingresos!$C$68 -> 2498.366 | D45: =Ingresos!$D$68 -> 4466.4375 | E45: =Ingresos!$E$68 -> 7499.5059
A46: EBITDA (lo que queda antes de impuestos y de pagar la obra) | B46: M MXN/año | C46: =Costos_Operacion!$C$45-Costos_Operacion!$C$42 -> 616.79651 | D46: =Costos_Operacion!$D$45-Costos_Operacion!$D$42 -> 2748.3409 | E46: =Costos_Operacion!$E$45-Costos_Operacion!$E$42 -> 5871.5708
A47: Margen | B47: % | C47: =Costos_Operacion!$C$46/Costos_Operacion!$C$45 -> 0.24687996 | D47: =Costos_Operacion!$D$46/Costos_Operacion!$D$45 -> 0.61533178 | E47: =Costos_Operacion!$E$46/Costos_Operacion!$E$45 -> 0.78292769

Sheet Flujo_30_anios
A1: Flujo de efectivo: 4 años de obra + 30 años de operación
A2: Millones de MXN de 2026. Los ingresos y costos estables vienen de las hojas Ingresos y Costos_Operacion; los paneles pierden 0.5 % al año y esa energía se compra a la red.
A4: Escenario Conservador
A5: Año | C5: Obra 1 | D5: Obra 2 | E5: Obra 3 | F5: Obra 4 | G5: 1 | H5: 2 | I5: 3 | J5: 4 | K5: 5 | L5: 6 | M5: 7 | N5: 8 | O5: 9 | P5: 10 | Q5: 11 | R5: 12 | S5: 13 | T5: 14 | U5: 15 | V5: 16 | W5: 17 | X5: 18 | Y5: 19 | Z5: 20 | AA5: 21 | AB5: 22 | AC5: 23 | AD5: 24 | AE5: 25 | AF5: 26 | AG5: 27 | AH5: 28 | AI5: 29 | AJ5: 30
A6: Fase | C6: =Supuestos!$C$14 -> 0.2 | D6: =Supuestos!$C$15 -> 0.3 | E6: =Supuestos!$C$16 -> 0.3 | F6: =Supuestos!$C$17 -> 0.2 | G6: =Supuestos!$C$18 -> 0.8 | H6: =Supuestos!$C$19 -> 0.9 | I6: 1 | J6: 1 | K6: 1 | L6: 1 | M6: 1 | N6: 1 | O6: 1 | P6: 1 | Q6: 1 | R6: 1 | S6: 1 | T6: 1 | U6: 1 | V6: 1 | W6: 1 | X6: 1 | Y6: 1 | Z6: 1 | AA6: 1 | AB6: 1 | AC6: 1 | AD6: 1 | AE6: 1 | AF6: 1 | AG6: 1 | AH6: 1 | AI6: 1 | AJ6: 1
A7: Inversión | C7: =-(Supuestos!$C$8+Supuestos!$C$13)*C6 -> -10729 | D7: =-(Supuestos!$C$8+Supuestos!$C$13)*D6 -> -16093.5 | E7: =-(Supuestos!$C$8+Supuestos!$C$13)*E6 -> -16093.5 | F7: =-(Supuestos!$C$8+Supuestos!$C$13)*F6 -> -10729 | G7: 0 | H7: 0 | I7: 0 | J7: 0 | K7: 0 | L7: 0 | M7: 0 | N7: 0 | O7: 0 | P7: 0 | Q7: 0 | R7: 0 | S7: 0 | T7: 0 | U7: 0 | V7: 0 | W7: 0 | X7: 0 | Y7: 0 | Z7: 0 | AA7: 0 | AB7: 0 | AC7: 0 | AD7: 0 | AE7: 0 | AF7: 0 | AG7: 0 | AH7: 0 | AI7: 0 | AJ7: 0
A8: Ingresos | C8: 0 | D8: 0 | E8: 0 | F8: 0 | G8: =Ingresos!$C$68*G6 -> 1998.6928 | H8: =Ingresos!$C$68*H6 -> 2248.5294 | I8: =Ingresos!$C$68*I6 -> 2498.366 | J8: =Ingresos!$C$68*J6 -> 2498.366 | K8: =Ingresos!$C$68*K6 -> 2498.366 | L8: =Ingresos!$C$68*L6 -> 2498.366 | M8: =Ingresos!$C$68*M6 -> 2498.366 | N8: =Ingresos!$C$68*N6 -> 2498.366 | ... AJ8: =Ingresos!$C$68*AJ6 -> 2498.366
A9: Costos de operación | C9: 0 | D9: 0 | E9: 0 | F9: 0 | G9: =-Costos_Operacion!$C$42 -> -1881.5695 | H9: =-Costos_Operacion!$C$42 -> -1881.5695 | I9: =-Costos_Operacion!$C$42 -> -1881.5695 | J9: =-Costos_Operacion!$C$42 -> -1881.5695 | K9: =-Costos_Operacion!$C$42 -> -1881.5695 | L9: =-Costos_Operacion!$C$42 -> -1881.5695 | M9: =-Costos_Operacion!$C$42 -> -1881.5695 | N9: =-Costos_Operacion!$C$42 -> -1881.5695 | ... AJ9: =-Costos_Operacion!$C$42 -> -1881.5695
A10: Energía extra por degradación de paneles | C10: 0 | D10: 0 | E10: 0 | F10: 0 | G10: =-Energia!$C$20*(1-(1-Supuestos!$C$146)^(1-1))*Supuestos!$C$153 -> 0 | H10: =-Energia!$C$20*(1-(1-Supuestos!$C$146)^(2-1))*Supuestos!$C$153 -> -0.21530673 | I10: =-Energia!$C$20*(1-(1-Supuestos!$C$146)^(3-1))*Supuestos!$C$153 -> -0.42953693 | J10: =-Energia!$C$20*(1-(1-Supuestos!$C$146)^(4-1))*Supuestos!$C$153 -> -0.64269597 | K10: =-Energia!$C$20*(1-(1-Supuestos!$C$146)^(5-1))*Supuestos!$C$153 -> -0.85478922 | L10: =-Energia!$C$20*(1-(1-Supuestos!$C$146)^(6-1))*Supuestos!$C$153 -> -1.065822 | M10: =-Energia!$C$20*(1-(1-Supuestos!$C$146)^(7-1))*Supuestos!$C$153 -> -1.2757996 | N10: =-Energia!$C$20*(1-(1-Supuestos!$C$146)^(8-1))*Supuestos!$C$153 -> -1.4847274 | O10: =-Energia!$C$20*(1-(1-Supuestos!$C$146)^(9-1))*Supuestos!$C$153 -> -1.6926104 | P10: =-Energia!$C$20*(1-(1-Supuestos!$C$146)^(10-1))*Supuestos!$C$153 -> -1.8994541 | Q10: =-Energia!$C$20*(1-(1-Supuestos!$C$146)^(11-1))*Supuestos!$C$153 -> -2.1052636 | R10: =-Energia!$C$20*(1-(1-Supuestos!$C$146)^(12-1))*Supuestos!$C$153 -> -2.310044 | S10: =-Energia!$C$20*(1-(1-Supuestos!$C$146)^(13-1))*Supuestos!$C$153 -> -2.5138005 | T10: =-Energia!$C$20*(1-(1-Supuestos!$C$146)^(14-1))*Supuestos!$C$153 -> -2.7165382 | U10: =-Energia!$C$20*(1-(1-Supuestos!$C$146)^(15-1))*Supuestos!$C$153 -> -2.9182623 | V10: =-Energia!$C$20*(1-(1-Supuestos!$C$146)^(16-1))*Supuestos!$C$153 -> -3.1189777 | W10: =-Energia!$C$20*(1-(1-Supuestos!$C$146)^(17-1))*Supuestos!$C$153 -> -3.3186895 | X10: =-Energia!$C$20*(1-(1-Supuestos!$C$146)^(18-1))*Supuestos!$C$153 -> -3.5174028 | Y10: =-Energia!$C$20*(1-(1-Supuestos!$C$146)^(19-1))*Supuestos!$C$153 -> -3.7151225 | Z10: =-Energia!$C$20*(1-(1-Supuestos!$C$146)^(20-1))*Supuestos!$C$153 -> -3.9118536 | AA10: =-Energia!$C$20*(1-(1-Supuestos!$C$146)^(21-1))*Supuestos!$C$153 -> -4.1076011 | AB10: =-Energia!$C$20*(1-(1-Supuestos!$C$146)^(22-1))*Supuestos!$C$153 -> -4.3023698 | AC10: =-Energia!$C$20*(1-(1-Supuestos!$C$146)^(23-1))*Supuestos!$C$153 -> -4.4961647 | AD10: =-Energia!$C$20*(1-(1-Supuestos!$C$146)^(24-1))*Supuestos!$C$153 -> -4.6889906 | AE10: =-Energia!$C$20*(1-(1-Supuestos!$C$146)^(25-1))*Supuestos!$C$153 -> -4.8808524 | AF10: =-Energia!$C$20*(1-(1-Supuestos!$C$146)^(26-1))*Supuestos!$C$153 -> -5.0717549 | AG10: =-Energia!$C$20*(1-(1-Supuestos!$C$146)^(27-1))*Supuestos!$C$153 -> -5.2617028 | AH10: =-Energia!$C$20*(1-(1-Supuestos!$C$146)^(28-1))*Supuestos!$C$153 -> -5.450701 | AI10: =-Energia!$C$20*(1-(1-Supuestos!$C$146)^(29-1))*Supuestos!$C$153 -> -5.6387543 | AJ10: =-Energia!$C$20*(1-(1-Supuestos!$C$146)^(30-1))*Supuestos!$C$153 -> -5.8258672
A11: EBITDA | C11: =C8+C9+C10 -> 0 | D11: =D8+D9+D10 -> 0 | E11: =E8+E9+E10 -> 0 | F11: =F8+F9+F10 -> 0 | G11: =G8+G9+G10 -> 117.12331 | H11: =H8+H9+H10 -> 366.7446 | I11: =I8+I9+I10 -> 616.36697 | J11: =J8+J9+J10 -> 616.15381 | ... AJ11: =AJ8+AJ9+AJ10 -> 610.97064
A12: Depreciación fiscal | C12: 0 | D12: 0 | E12: 0 | F12: 0 | G12: =IF(1<=1/Supuestos!$C$22,(Supuestos!$C$8)*Supuestos!$C$22,0) -> 2662.25 | H12: =IF(2<=1/Supuestos!$C$22,(Supuestos!$C$8)*Supuestos!$C$22,0) -> 2662.25 | I12: =IF(3<=1/Supuestos!$C$22,(Supuestos!$C$8)*Supuestos!$C$22,0) -> 2662.25 | J12: =IF(4<=1/Supuestos!$C$22,(Supuestos!$C$8)*Supuestos!$C$22,0) -> 2662.25 | K12: =IF(5<=1/Supuestos!$C$22,(Supuestos!$C$8)*Supuestos!$C$22,0) -> 2662.25 | L12: =IF(6<=1/Supuestos!$C$22,(Supuestos!$C$8)*Supuestos!$C$22,0) -> 2662.25 | M12: =IF(7<=1/Supuestos!$C$22,(Supuestos!$C$8)*Supuestos!$C$22,0) -> 2662.25 | N12: =IF(8<=1/Supuestos!$C$22,(Supuestos!$C$8)*Supuestos!$C$22,0) -> 2662.25 | O12: =IF(9<=1/Supuestos!$C$22,(Supuestos!$C$8)*Supuestos!$C$22,0) -> 2662.25 | P12: =IF(10<=1/Supuestos!$C$22,(Supuestos!$C$8)*Supuestos!$C$22,0) -> 2662.25 | Q12: =IF(11<=1/Supuestos!$C$22,(Supuestos!$C$8)*Supuestos!$C$22,0) -> 2662.25 | R12: =IF(12<=1/Supuestos!$C$22,(Supuestos!$C$8)*Supuestos!$C$22,0) -> 2662.25 | S12: =IF(13<=1/Supuestos!$C$22,(Supuestos!$C$8)*Supuestos!$C$22,0) -> 2662.25 | T12: =IF(14<=1/Supuestos!$C$22,(Supuestos!$C$8)*Supuestos!$C$22,0) -> 2662.25 | U12: =IF(15<=1/Supuestos!$C$22,(Supuestos!$C$8)*Supuestos!$C$22,0) -> 2662.25 | V12: =IF(16<=1/Supuestos!$C$22,(Supuestos!$C$8)*Supuestos!$C$22,0) -> 2662.25 | W12: =IF(17<=1/Supuestos!$C$22,(Supuestos!$C$8)*Supuestos!$C$22,0) -> 2662.25 | X12: =IF(18<=1/Supuestos!$C$22,(Supuestos!$C$8)*Supuestos!$C$22,0) -> 2662.25 | Y12: =IF(19<=1/Supuestos!$C$22,(Supuestos!$C$8)*Supuestos!$C$22,0) -> 2662.25 | Z12: =IF(20<=1/Supuestos!$C$22,(Supuestos!$C$8)*Supuestos!$C$22,0) -> 2662.25 | AA12: =IF(21<=1/Supuestos!$C$22,(Supuestos!$C$8)*Supuestos!$C$22,0) -> 0 | AB12: =IF(22<=1/Supuestos!$C$22,(Supuestos!$C$8)*Supuestos!$C$22,0) -> 0 | AC12: =IF(23<=1/Supuestos!$C$22,(Supuestos!$C$8)*Supuestos!$C$22,0) -> 0 | AD12: =IF(24<=1/Supuestos!$C$22,(Supuestos!$C$8)*Supuestos!$C$22,0) -> 0 | AE12: =IF(25<=1/Supuestos!$C$22,(Supuestos!$C$8)*Supuestos!$C$22,0) -> 0 | AF12: =IF(26<=1/Supuestos!$C$22,(Supuestos!$C$8)*Supuestos!$C$22,0) -> 0 | AG12: =IF(27<=1/Supuestos!$C$22,(Supuestos!$C$8)*Supuestos!$C$22,0) -> 0 | AH12: =IF(28<=1/Supuestos!$C$22,(Supuestos!$C$8)*Supuestos!$C$22,0) -> 0 | AI12: =IF(29<=1/Supuestos!$C$22,(Supuestos!$C$8)*Supuestos!$C$22,0) -> 0 | AJ12: =IF(30<=1/Supuestos!$C$22,(Supuestos!$C$8)*Supuestos!$C$22,0) -> 0
A13: ISR | C13: =-MAX(0,C11-C12)*Supuestos!$C$21 -> 0 | D13: =-MAX(0,D11-D12)*Supuestos!$C$21 -> 0 | E13: =-MAX(0,E11-E12)*Supuestos!$C$21 -> 0 | F13: =-MAX(0,F11-F12)*Supuestos!$C$21 -> 0 | G13: =-MAX(0,G11-G12)*Supuestos!$C$21 -> 0 | H13: =-MAX(0,H11-H12)*Supuestos!$C$21 -> 0 | I13: =-MAX(0,I11-I12)*Supuestos!$C$21 -> 0 | J13: =-MAX(0,J11-J12)*Supuestos!$C$21 -> 0 | ... AJ13: =-MAX(0,AJ11-AJ12)*Supuestos!$C$21 -> -183.29119
A14: Flujo antes de impuestos | C14: =C7+C11 -> -10729 | D14: =D7+D11 -> -16093.5 | E14: =E7+E11 -> -16093.5 | F14: =F7+F11 -> -10729 | G14: =G7+G11 -> 117.12331 | H14: =H7+H11 -> 366.7446 | I14: =I7+I11 -> 616.36697 | J14: =J7+J11 -> 616.15381 | ... AJ14: =AJ7+AJ11 -> 610.97064
A15: Flujo después de impuestos | C15: =C14+C13 -> -10729 | D15: =D14+D13 -> -16093.5 | E15: =E14+E13 -> -16093.5 | F15: =F14+F13 -> -10729 | G15: =G14+G13 -> 117.12331 | H15: =H14+H13 -> 366.7446 | I15: =I14+I13 -> 616.36697 | J15: =J14+J13 -> 616.15381 | ... AJ15: =AJ14+AJ13 -> 427.67945
A16: Acumulado | C16: =C15 -> -10729 | D16: =C16+D15 -> -26822.5 | E16: =D16+E15 -> -42916 | F16: =E16+F15 -> -53645 | G16: =F16+G15 -> -53527.877 | H16: =G16+H15 -> -53161.132 | I16: =H16+I15 -> -52544.765 | J16: =I16+J15 -> -51928.611 | K16: =J16+K15 -> -51312.67 | ... AJ16: =AI16+AJ15 -> -37815.518
A17: Flujo descontado | C17: =C15/(1+Supuestos!$C$20)^0 -> -10729 | D17: =D15/(1+Supuestos!$C$20)^1 -> -14764.679 | E17: =E15/(1+Supuestos!$C$20)^2 -> -13545.577 | F17: =F15/(1+Supuestos!$C$20)^3 -> -8284.7566 | G17: =G15/(1+Supuestos!$C$20)^4 -> 82.973104 | H17: =H15/(1+Supuestos!$C$20)^5 -> 238.35883 | I17: =I15/(1+Supuestos!$C$20)^6 -> 367.51949 | J17: =J15/(1+Supuestos!$C$20)^7 -> 337.05724 | K17: =K15/(1+Supuestos!$C$20)^8 -> 309.12038 | L17: =L15/(1+Supuestos!$C$20)^9 -> 283.49951 | M17: =M15/(1+Supuestos!$C$20)^10 -> 260.0026 | N17: =N15/(1+Supuestos!$C$20)^11 -> 238.45353 | O17: =O15/(1+Supuestos!$C$20)^12 -> 218.6908 | P17: =P15/(1+Supuestos!$C$20)^13 -> 200.56629 | Q17: =Q15/(1+Supuestos!$C$20)^14 -> 183.94418 | R17: =R15/(1+Supuestos!$C$20)^15 -> 168.69991 | S17: =S15/(1+Supuestos!$C$20)^16 -> 154.71924 | T17: =T15/(1+Supuestos!$C$20)^17 -> 141.89741 | U17: =U15/(1+Supuestos!$C$20)^18 -> 130.13835 | V17: =V15/(1+Supuestos!$C$20)^19 -> 119.35394 | W17: =W15/(1+Supuestos!$C$20)^20 -> 109.46339 | X17: =X15/(1+Supuestos!$C$20)^21 -> 100.3926 | Y17: =Y15/(1+Supuestos!$C$20)^22 -> 92.073611 | Z17: =Z15/(1+Supuestos!$C$20)^23 -> 84.444097 | AA17: =AA15/(1+Supuestos!$C$20)^24 -> 54.212834 | AB17: =AB15/(1+Supuestos!$C$20)^25 -> 49.720734 | AC17: =AC15/(1+Supuestos!$C$20)^26 -> 45.600919 | AD17: =AD15/(1+Supuestos!$C$20)^27 -> 41.822531 | AE17: =AE15/(1+Supuestos!$C$20)^28 -> 38.357268 | AF17: =AF15/(1+Supuestos!$C$20)^29 -> 35.179175 | AG17: =AG15/(1+Supuestos!$C$20)^30 -> 32.264451 | AH17: =AH15/(1+Supuestos!$C$20)^31 -> 29.591266 | AI17: =AI15/(1+Supuestos!$C$20)^32 -> 27.139599 | AJ17: =AJ15/(1+Supuestos!$C$20)^33 -> 24.891092
A18: Acumulado descontado | C18: =C17 -> -10729 | D18: =C18+D17 -> -25493.679 | E18: =D18+E17 -> -39039.256 | F18: =E18+F17 -> -47324.012 | G18: =F18+G17 -> -47241.039 | H18: =G18+H17 -> -47002.68 | I18: =H18+I17 -> -46635.161 | J18: =I18+J17 -> -46298.104 | K18: =J18+K17 -> -45988.983 | ... AJ18: =AI18+AJ17 -> -43123.864
A19: VPN a la tasa real (después de impuestos) | B19: =SUM(C17:AJ17) -> -43123.864
A20: TIR real antes de impuestos | B20: =IFERROR(IRR(C14:AJ14,0.02),IFERROR(IRR(C14:AJ14,-0.05),"negativa")) -> -0.055436918
A21: TIR real después de impuestos | B21: =IFERROR(IRR(C15:AJ15,0.02),IFERROR(IRR(C15:AJ15,-0.05),"negativa")) -> -0.063561192
A22: Recuperación (años desde la apertura) | B22: =IF(COUNTIF(G16:AJ16,"<0")>=30,"más de 30",COUNTIF(G16:AJ16,"<0")+1) -> más de 30
A23: Recuperación descontada (años desde la apertura) | B23: =IF(COUNTIF(G18:AJ18,"<0")>=30,"más de 30",COUNTIF(G18:AJ18,"<0")+1) -> más de 30
A24: Efectivo acumulado al año 30 | B24: =AJ16 -> -37815.518
A27: Escenario Base
A28: Año | C28: Obra 1 | D28: Obra 2 | E28: Obra 3 | F28: Obra 4 | G28: 1 | H28: 2 | I28: 3 | J28: 4 | K28: 5 | L28: 6 | M28: 7 | N28: 8 | O28: 9 | P28: 10 | Q28: 11 | R28: 12 | S28: 13 | T28: 14 | U28: 15 | V28: 16 | W28: 17 | X28: 18 | Y28: 19 | Z28: 20 | AA28: 21 | AB28: 22 | AC28: 23 | AD28: 24 | AE28: 25 | AF28: 26 | AG28: 27 | AH28: 28 | AI28: 29 | AJ28: 30
A29: Fase | C29: =Supuestos!$D$14 -> 0.2 | D29: =Supuestos!$D$15 -> 0.3 | E29: =Supuestos!$D$16 -> 0.3 | F29: =Supuestos!$D$17 -> 0.2 | G29: =Supuestos!$D$18 -> 0.85 | H29: =Supuestos!$D$19 -> 0.95 | I29: 1 | J29: 1 | K29: 1 | L29: 1 | M29: 1 | N29: 1 | O29: 1 | P29: 1 | Q29: 1 | R29: 1 | S29: 1 | T29: 1 | U29: 1 | V29: 1 | W29: 1 | X29: 1 | Y29: 1 | Z29: 1 | AA29: 1 | AB29: 1 | AC29: 1 | AD29: 1 | AE29: 1 | AF29: 1 | AG29: 1 | AH29: 1 | AI29: 1 | AJ29: 1
A30: Inversión | C30: =-(Supuestos!$D$8+Supuestos!$D$13)*C29 -> -10709 | D30: =-(Supuestos!$D$8+Supuestos!$D$13)*D29 -> -16063.5 | E30: =-(Supuestos!$D$8+Supuestos!$D$13)*E29 -> -16063.5 | F30: =-(Supuestos!$D$8+Supuestos!$D$13)*F29 -> -10709 | G30: 0 | H30: 0 | I30: 0 | J30: 0 | K30: 0 | L30: 0 | M30: 0 | N30: 0 | O30: 0 | P30: 0 | Q30: 0 | R30: 0 | S30: 0 | T30: 0 | U30: 0 | V30: 0 | W30: 0 | X30: 0 | Y30: 0 | Z30: 0 | AA30: 0 | AB30: 0 | AC30: 0 | AD30: 0 | AE30: 0 | AF30: 0 | AG30: 0 | AH30: 0 | AI30: 0 | AJ30: 0
A31: Ingresos | C31: 0 | D31: 0 | E31: 0 | F31: 0 | G31: =Ingresos!$D$68*G29 -> 3796.4719 | H31: =Ingresos!$D$68*H29 -> 4243.1156 | I31: =Ingresos!$D$68*I29 -> 4466.4375 | J31: =Ingresos!$D$68*J29 -> 4466.4375 | K31: =Ingresos!$D$68*K29 -> 4466.4375 | L31: =Ingresos!$D$68*L29 -> 4466.4375 | M31: =Ingresos!$D$68*M29 -> 4466.4375 | N31: =Ingresos!$D$68*N29 -> 4466.4375 | ... AJ31: =Ingresos!$D$68*AJ29 -> 4466.4375
A32: Costos de operación | C32: 0 | D32: 0 | E32: 0 | F32: 0 | G32: =-Costos_Operacion!$D$42 -> -1718.0966 | H32: =-Costos_Operacion!$D$42 -> -1718.0966 | I32: =-Costos_Operacion!$D$42 -> -1718.0966 | J32: =-Costos_Operacion!$D$42 -> -1718.0966 | K32: =-Costos_Operacion!$D$42 -> -1718.0966 | L32: =-Costos_Operacion!$D$42 -> -1718.0966 | M32: =-Costos_Operacion!$D$42 -> -1718.0966 | N32: =-Costos_Operacion!$D$42 -> -1718.0966 | ... AJ32: =-Costos_Operacion!$D$42 -> -1718.0966
A33: Energía extra por degradación de paneles | C33: 0 | D33: 0 | E33: 0 | F33: 0 | G33: =-Energia!$D$20*(1-(1-Supuestos!$D$146)^(1-1))*Supuestos!$D$153 -> 0 | H33: =-Energia!$D$20*(1-(1-Supuestos!$D$146)^(2-1))*Supuestos!$D$153 -> -0.22294649 | I33: =-Energia!$D$20*(1-(1-Supuestos!$D$146)^(3-1))*Supuestos!$D$153 -> -0.44477825 | J33: =-Energia!$D$20*(1-(1-Supuestos!$D$146)^(4-1))*Supuestos!$D$153 -> -0.66550085 | K33: =-Energia!$D$20*(1-(1-Supuestos!$D$146)^(5-1))*Supuestos!$D$153 -> -0.88511984 | L33: =-Energia!$D$20*(1-(1-Supuestos!$D$146)^(6-1))*Supuestos!$D$153 -> -1.1036407 | M33: =-Energia!$D$20*(1-(1-Supuestos!$D$146)^(7-1))*Supuestos!$D$153 -> -1.321069 | N33: =-Energia!$D$20*(1-(1-Supuestos!$D$146)^(8-1))*Supuestos!$D$153 -> -1.5374102 | O33: =-Energia!$D$20*(1-(1-Supuestos!$D$146)^(9-1))*Supuestos!$D$153 -> -1.7526696 | P33: =-Energia!$D$20*(1-(1-Supuestos!$D$146)^(10-1))*Supuestos!$D$153 -> -1.9668527 | Q33: =-Energia!$D$20*(1-(1-Supuestos!$D$146)^(11-1))*Supuestos!$D$153 -> -2.179965 | R33: =-Energia!$D$20*(1-(1-Supuestos!$D$146)^(12-1))*Supuestos!$D$153 -> -2.3920116 | S33: =-Energia!$D$20*(1-(1-Supuestos!$D$146)^(13-1))*Supuestos!$D$153 -> -2.6029981 | T33: =-Energia!$D$20*(1-(1-Supuestos!$D$146)^(14-1))*Supuestos!$D$153 -> -2.8129296 | U33: =-Energia!$D$20*(1-(1-Supuestos!$D$146)^(15-1))*Supuestos!$D$153 -> -3.0218114 | V33: =-Energia!$D$20*(1-(1-Supuestos!$D$146)^(16-1))*Supuestos!$D$153 -> -3.2296488 | W33: =-Energia!$D$20*(1-(1-Supuestos!$D$146)^(17-1))*Supuestos!$D$153 -> -3.4364471 | X33: =-Energia!$D$20*(1-(1-Supuestos!$D$146)^(18-1))*Supuestos!$D$153 -> -3.6422113 | Y33: =-Energia!$D$20*(1-(1-Supuestos!$D$146)^(19-1))*Supuestos!$D$153 -> -3.8469468 | Z33: =-Energia!$D$20*(1-(1-Supuestos!$D$146)^(20-1))*Supuestos!$D$153 -> -4.0506585 | AA33: =-Energia!$D$20*(1-(1-Supuestos!$D$146)^(21-1))*Supuestos!$D$153 -> -4.2533517 | AB33: =-Energia!$D$20*(1-(1-Supuestos!$D$146)^(22-1))*Supuestos!$D$153 -> -4.4550315 | AC33: =-Energia!$D$20*(1-(1-Supuestos!$D$146)^(23-1))*Supuestos!$D$153 -> -4.6557028 | AD33: =-Energia!$D$20*(1-(1-Supuestos!$D$146)^(24-1))*Supuestos!$D$153 -> -4.8553708 | AE33: =-Energia!$D$20*(1-(1-Supuestos!$D$146)^(25-1))*Supuestos!$D$153 -> -5.0540404 | AF33: =-Energia!$D$20*(1-(1-Supuestos!$D$146)^(26-1))*Supuestos!$D$153 -> -5.2517167 | AG33: =-Energia!$D$20*(1-(1-Supuestos!$D$146)^(27-1))*Supuestos!$D$153 -> -5.4484046 | AH33: =-Energia!$D$20*(1-(1-Supuestos!$D$146)^(28-1))*Supuestos!$D$153 -> -5.6441091 | AI33: =-Energia!$D$20*(1-(1-Supuestos!$D$146)^(29-1))*Supuestos!$D$153 -> -5.838835 | AJ33: =-Energia!$D$20*(1-(1-Supuestos!$D$146)^(30-1))*Supuestos!$D$153 -> -6.0325873
A34: EBITDA | C34: =C31+C32+C33 -> 0 | D34: =D31+D32+D33 -> 0 | E34: =E31+E32+E33 -> 0 | F34: =F31+F32+F33 -> 0 | G34: =G31+G32+G33 -> 2078.3753 | H34: =H31+H32+H33 -> 2524.7961 | I34: =I31+I32+I33 -> 2747.8961 | J34: =J31+J32+J33 -> 2747.6754 | ... AJ34: =AJ31+AJ32+AJ33 -> 2742.3083
A35: Depreciación fiscal | C35: 0 | D35: 0 | E35: 0 | F35: 0 | G35: =IF(1<=1/Supuestos!$D$22,(Supuestos!$D$8)*Supuestos!$D$22,0) -> 2662.25 | H35: =IF(2<=1/Supuestos!$D$22,(Supuestos!$D$8)*Supuestos!$D$22,0) -> 2662.25 | I35: =IF(3<=1/Supuestos!$D$22,(Supuestos!$D$8)*Supuestos!$D$22,0) -> 2662.25 | J35: =IF(4<=1/Supuestos!$D$22,(Supuestos!$D$8)*Supuestos!$D$22,0) -> 2662.25 | K35: =IF(5<=1/Supuestos!$D$22,(Supuestos!$D$8)*Supuestos!$D$22,0) -> 2662.25 | L35: =IF(6<=1/Supuestos!$D$22,(Supuestos!$D$8)*Supuestos!$D$22,0) -> 2662.25 | M35: =IF(7<=1/Supuestos!$D$22,(Supuestos!$D$8)*Supuestos!$D$22,0) -> 2662.25 | N35: =IF(8<=1/Supuestos!$D$22,(Supuestos!$D$8)*Supuestos!$D$22,0) -> 2662.25 | O35: =IF(9<=1/Supuestos!$D$22,(Supuestos!$D$8)*Supuestos!$D$22,0) -> 2662.25 | P35: =IF(10<=1/Supuestos!$D$22,(Supuestos!$D$8)*Supuestos!$D$22,0) -> 2662.25 | Q35: =IF(11<=1/Supuestos!$D$22,(Supuestos!$D$8)*Supuestos!$D$22,0) -> 2662.25 | R35: =IF(12<=1/Supuestos!$D$22,(Supuestos!$D$8)*Supuestos!$D$22,0) -> 2662.25 | S35: =IF(13<=1/Supuestos!$D$22,(Supuestos!$D$8)*Supuestos!$D$22,0) -> 2662.25 | T35: =IF(14<=1/Supuestos!$D$22,(Supuestos!$D$8)*Supuestos!$D$22,0) -> 2662.25 | U35: =IF(15<=1/Supuestos!$D$22,(Supuestos!$D$8)*Supuestos!$D$22,0) -> 2662.25 | V35: =IF(16<=1/Supuestos!$D$22,(Supuestos!$D$8)*Supuestos!$D$22,0) -> 2662.25 | W35: =IF(17<=1/Supuestos!$D$22,(Supuestos!$D$8)*Supuestos!$D$22,0) -> 2662.25 | X35: =IF(18<=1/Supuestos!$D$22,(Supuestos!$D$8)*Supuestos!$D$22,0) -> 2662.25 | Y35: =IF(19<=1/Supuestos!$D$22,(Supuestos!$D$8)*Supuestos!$D$22,0) -> 2662.25 | Z35: =IF(20<=1/Supuestos!$D$22,(Supuestos!$D$8)*Supuestos!$D$22,0) -> 2662.25 | AA35: =IF(21<=1/Supuestos!$D$22,(Supuestos!$D$8)*Supuestos!$D$22,0) -> 0 | AB35: =IF(22<=1/Supuestos!$D$22,(Supuestos!$D$8)*Supuestos!$D$22,0) -> 0 | AC35: =IF(23<=1/Supuestos!$D$22,(Supuestos!$D$8)*Supuestos!$D$22,0) -> 0 | AD35: =IF(24<=1/Supuestos!$D$22,(Supuestos!$D$8)*Supuestos!$D$22,0) -> 0 | AE35: =IF(25<=1/Supuestos!$D$22,(Supuestos!$D$8)*Supuestos!$D$22,0) -> 0 | AF35: =IF(26<=1/Supuestos!$D$22,(Supuestos!$D$8)*Supuestos!$D$22,0) -> 0 | AG35: =IF(27<=1/Supuestos!$D$22,(Supuestos!$D$8)*Supuestos!$D$22,0) -> 0 | AH35: =IF(28<=1/Supuestos!$D$22,(Supuestos!$D$8)*Supuestos!$D$22,0) -> 0 | AI35: =IF(29<=1/Supuestos!$D$22,(Supuestos!$D$8)*Supuestos!$D$22,0) -> 0 | AJ35: =IF(30<=1/Supuestos!$D$22,(Supuestos!$D$8)*Supuestos!$D$22,0) -> 0
A36: ISR | C36: =-MAX(0,C34-C35)*Supuestos!$D$21 -> 0 | D36: =-MAX(0,D34-D35)*Supuestos!$D$21 -> 0 | E36: =-MAX(0,E34-E35)*Supuestos!$D$21 -> 0 | F36: =-MAX(0,F34-F35)*Supuestos!$D$21 -> 0 | G36: =-MAX(0,G34-G35)*Supuestos!$D$21 -> 0 | H36: =-MAX(0,H34-H35)*Supuestos!$D$21 -> 0 | I36: =-MAX(0,I34-I35)*Supuestos!$D$21 -> -25.693843 | J36: =-MAX(0,J34-J35)*Supuestos!$D$21 -> -25.627626 | ... AJ36: =-MAX(0,AJ34-AJ35)*Supuestos!$D$21 -> -822.6925
A37: Flujo antes de impuestos | C37: =C30+C34 -> -10709 | D37: =D30+D34 -> -16063.5 | E37: =E30+E34 -> -16063.5 | F37: =F30+F34 -> -10709 | G37: =G30+G34 -> 2078.3753 | H37: =H30+H34 -> 2524.7961 | I37: =I30+I34 -> 2747.8961 | J37: =J30+J34 -> 2747.6754 | ... AJ37: =AJ30+AJ34 -> 2742.3083
A38: Flujo después de impuestos | C38: =C37+C36 -> -10709 | D38: =D37+D36 -> -16063.5 | E38: =E37+E36 -> -16063.5 | F38: =F37+F36 -> -10709 | G38: =G37+G36 -> 2078.3753 | H38: =H37+H36 -> 2524.7961 | I38: =I37+I36 -> 2722.2023 | J38: =J37+J36 -> 2722.0478 | ... AJ38: =AJ37+AJ36 -> 1919.6158
A39: Acumulado | C39: =C38 -> -10709 | D39: =C39+D38 -> -26772.5 | E39: =D39+E38 -> -42836 | F39: =E39+F38 -> -53545 | G39: =F39+G38 -> -51466.625 | H39: =G39+H38 -> -48941.829 | I39: =H39+I38 -> -46219.626 | J39: =I39+J38 -> -43497.579 | K39: =J39+K38 -> -40775.684 | ... AJ39: =AI39+AJ38 -> 19237.136
A40: Flujo descontado | C40: =C38/(1+Supuestos!$D$20)^0 -> -10709 | D40: =D38/(1+Supuestos!$D$20)^1 -> -14873.611 | E40: =E38/(1+Supuestos!$D$20)^2 -> -13771.862 | F40: =F38/(1+Supuestos!$D$20)^3 -> -8501.1495 | G40: =G38/(1+Supuestos!$D$20)^4 -> 1527.6679 | H40: =H38/(1+Supuestos!$D$20)^5 -> 1718.3338 | I40: =I38/(1+Supuestos!$D$20)^6 -> 1715.4492 | J40: =J38/(1+Supuestos!$D$20)^7 -> 1588.2887 | K40: =K38/(1+Supuestos!$D$20)^8 -> 1470.5547 | L40: =L38/(1+Supuestos!$D$20)^9 -> 1361.5482 | M40: =M38/(1+Supuestos!$D$20)^10 -> 1260.6223 | N40: =N38/(1+Supuestos!$D$20)^11 -> 1167.1779 | O40: =O38/(1+Supuestos!$D$20)^12 -> 1080.6604 | P40: =P38/(1+Supuestos!$D$20)^13 -> 1000.5564 | Q40: =Q38/(1+Supuestos!$D$20)^14 -> 926.3903 | R40: =R38/(1+Supuestos!$D$20)^15 -> 857.722 | S40: =S38/(1+Supuestos!$D$20)^16 -> 794.14393 | T40: =T38/(1+Supuestos!$D$20)^17 -> 735.27873 | U40: =U38/(1+Supuestos!$D$20)^18 -> 680.77705 | V40: =V38/(1+Supuestos!$D$20)^19 -> 630.31541 | W40: =W38/(1+Supuestos!$D$20)^20 -> 583.59432 | X40: =X38/(1+Supuestos!$D$20)^21 -> 540.3365 | Y40: =Y38/(1+Supuestos!$D$20)^22 -> 500.28521 | Z40: =Z38/(1+Supuestos!$D$20)^23 -> 463.20276 | AA40: =AA38/(1+Supuestos!$D$20)^24 -> 302.91855 | AB40: =AB38/(1+Supuestos!$D$20)^25 -> 280.45953 | AC40: =AC38/(1+Supuestos!$D$20)^26 -> 259.66576 | AD40: =AD38/(1+Supuestos!$D$20)^27 -> 240.41376 | AE40: =AE38/(1+Supuestos!$D$20)^28 -> 222.58921 | AF40: =AF38/(1+Supuestos!$D$20)^29 -> 206.08627 | AG40: =AG38/(1+Supuestos!$D$20)^30 -> 190.80694 | AH40: =AH38/(1+Supuestos!$D$20)^31 -> 176.66049 | AI40: =AI38/(1+Supuestos!$D$20)^32 -> 163.56291 | AJ40: =AJ38/(1+Supuestos!$D$20)^33 -> 151.43644
A41: Acumulado descontado | C41: =C40 -> -10709 | D41: =C41+D40 -> -25582.611 | E41: =D41+E40 -> -39354.473 | F41: =E41+F40 -> -47855.623 | G41: =F41+G40 -> -46327.955 | H41: =G41+H40 -> -44609.621 | I41: =H41+I40 -> -42894.172 | J41: =I41+J40 -> -41305.883 | K41: =J41+K40 -> -39835.328 | ... AJ41: =AI41+AJ40 -> -25058.117
A42: VPN a la tasa real (después de impuestos) | B42: =SUM(C40:AJ40) -> -25058.117
A43: TIR real antes de impuestos | B43: =IFERROR(IRR(C37:AJ37,0.02),IFERROR(IRR(C37:AJ37,-0.05),"negativa")) -> 0.026213253
A44: TIR real después de impuestos | B44: =IFERROR(IRR(C38:AJ38,0.02),IFERROR(IRR(C38:AJ38,-0.05),"negativa")) -> 0.02013905
A45: Recuperación (años desde la apertura) | B45: =IF(COUNTIF(G39:AJ39,"<0")>=30,"más de 30",COUNTIF(G39:AJ39,"<0")+1) -> 20
A46: Recuperación descontada (años desde la apertura) | B46: =IF(COUNTIF(G41:AJ41,"<0")>=30,"más de 30",COUNTIF(G41:AJ41,"<0")+1) -> más de 30
A47: Efectivo acumulado al año 30 | B47: =AJ39 -> 19237.136
A50: Escenario Optimista
A51: Año | C51: Obra 1 | D51: Obra 2 | E51: Obra 3 | F51: Obra 4 | G51: 1 | H51: 2 | I51: 3 | J51: 4 | K51: 5 | L51: 6 | M51: 7 | N51: 8 | O51: 9 | P51: 10 | Q51: 11 | R51: 12 | S51: 13 | T51: 14 | U51: 15 | V51: 16 | W51: 17 | X51: 18 | Y51: 19 | Z51: 20 | AA51: 21 | AB51: 22 | AC51: 23 | AD51: 24 | AE51: 25 | AF51: 26 | AG51: 27 | AH51: 28 | AI51: 29 | AJ51: 30
A52: Fase | C52: =Supuestos!$E$14 -> 0.2 | D52: =Supuestos!$E$15 -> 0.3 | E52: =Supuestos!$E$16 -> 0.3 | F52: =Supuestos!$E$17 -> 0.2 | G52: =Supuestos!$E$18 -> 0.9 | H52: =Supuestos!$E$19 -> 1 | I52: 1 | J52: 1 | K52: 1 | L52: 1 | M52: 1 | N52: 1 | O52: 1 | P52: 1 | Q52: 1 | R52: 1 | S52: 1 | T52: 1 | U52: 1 | V52: 1 | W52: 1 | X52: 1 | Y52: 1 | Z52: 1 | AA52: 1 | AB52: 1 | AC52: 1 | AD52: 1 | AE52: 1 | AF52: 1 | AG52: 1 | AH52: 1 | AI52: 1 | AJ52: 1
A53: Inversión | C53: =-(Supuestos!$E$8+Supuestos!$E$13)*C52 -> -10699 | D53: =-(Supuestos!$E$8+Supuestos!$E$13)*D52 -> -16048.5 | E53: =-(Supuestos!$E$8+Supuestos!$E$13)*E52 -> -16048.5 | F53: =-(Supuestos!$E$8+Supuestos!$E$13)*F52 -> -10699 | G53: 0 | H53: 0 | I53: 0 | J53: 0 | K53: 0 | L53: 0 | M53: 0 | N53: 0 | O53: 0 | P53: 0 | Q53: 0 | R53: 0 | S53: 0 | T53: 0 | U53: 0 | V53: 0 | W53: 0 | X53: 0 | Y53: 0 | Z53: 0 | AA53: 0 | AB53: 0 | AC53: 0 | AD53: 0 | AE53: 0 | AF53: 0 | AG53: 0 | AH53: 0 | AI53: 0 | AJ53: 0
A54: Ingresos | C54: 0 | D54: 0 | E54: 0 | F54: 0 | G54: =Ingresos!$E$68*G52 -> 6749.5553 | H54: =Ingresos!$E$68*H52 -> 7499.5059 | I54: =Ingresos!$E$68*I52 -> 7499.5059 | J54: =Ingresos!$E$68*J52 -> 7499.5059 | K54: =Ingresos!$E$68*K52 -> 7499.5059 | L54: =Ingresos!$E$68*L52 -> 7499.5059 | M54: =Ingresos!$E$68*M52 -> 7499.5059 | N54: =Ingresos!$E$68*N52 -> 7499.5059 | ... AJ54: =Ingresos!$E$68*AJ52 -> 7499.5059
A55: Costos de operación | C55: 0 | D55: 0 | E55: 0 | F55: 0 | G55: =-Costos_Operacion!$E$42 -> -1627.9351 | H55: =-Costos_Operacion!$E$42 -> -1627.9351 | I55: =-Costos_Operacion!$E$42 -> -1627.9351 | J55: =-Costos_Operacion!$E$42 -> -1627.9351 | K55: =-Costos_Operacion!$E$42 -> -1627.9351 | L55: =-Costos_Operacion!$E$42 -> -1627.9351 | M55: =-Costos_Operacion!$E$42 -> -1627.9351 | N55: =-Costos_Operacion!$E$42 -> -1627.9351 | ... AJ55: =-Costos_Operacion!$E$42 -> -1627.9351
A56: Energía extra por degradación de paneles | C56: 0 | D56: 0 | E56: 0 | F56: 0 | G56: =-Energia!$E$20*(1-(1-Supuestos!$E$146)^(1-1))*Supuestos!$E$153 -> 0 | H56: =-Energia!$E$20*(1-(1-Supuestos!$E$146)^(2-1))*Supuestos!$E$153 -> -0.23540181 | I56: =-Energia!$E$20*(1-(1-Supuestos!$E$146)^(3-1))*Supuestos!$E$153 -> -0.46962662 | J56: =-Energia!$E$20*(1-(1-Supuestos!$E$146)^(4-1))*Supuestos!$E$153 -> -0.7026803 | K56: =-Energia!$E$20*(1-(1-Supuestos!$E$146)^(5-1))*Supuestos!$E$153 -> -0.93456871 | L56: =-Energia!$E$20*(1-(1-Supuestos!$E$146)^(6-1))*Supuestos!$E$153 -> -1.1652977 | M56: =-Energia!$E$20*(1-(1-Supuestos!$E$146)^(7-1))*Supuestos!$E$153 -> -1.394873 | N56: =-Energia!$E$20*(1-(1-Supuestos!$E$146)^(8-1))*Supuestos!$E$153 -> -1.6233005 | O56: =-Energia!$E$20*(1-(1-Supuestos!$E$146)^(9-1))*Supuestos!$E$153 -> -1.8505858 | P56: =-Energia!$E$20*(1-(1-Supuestos!$E$146)^(10-1))*Supuestos!$E$153 -> -2.0767347 | Q56: =-Energia!$E$20*(1-(1-Supuestos!$E$146)^(11-1))*Supuestos!$E$153 -> -2.3017528 | R56: =-Energia!$E$20*(1-(1-Supuestos!$E$146)^(12-1))*Supuestos!$E$153 -> -2.5256458 | S56: =-Energia!$E$20*(1-(1-Supuestos!$E$146)^(13-1))*Supuestos!$E$153 -> -2.7484194 | T56: =-Energia!$E$20*(1-(1-Supuestos!$E$146)^(14-1))*Supuestos!$E$153 -> -2.9700791 | U56: =-Energia!$E$20*(1-(1-Supuestos!$E$146)^(15-1))*Supuestos!$E$153 -> -3.1906306 | V56: =-Energia!$E$20*(1-(1-Supuestos!$E$146)^(16-1))*Supuestos!$E$153 -> -3.4100792 | W56: =-Energia!$E$20*(1-(1-Supuestos!$E$146)^(17-1))*Supuestos!$E$153 -> -3.6284306 | X56: =-Energia!$E$20*(1-(1-Supuestos!$E$146)^(18-1))*Supuestos!$E$153 -> -3.8456903 | Y56: =-Energia!$E$20*(1-(1-Supuestos!$E$146)^(19-1))*Supuestos!$E$153 -> -4.0618637 | Z56: =-Energia!$E$20*(1-(1-Supuestos!$E$146)^(20-1))*Supuestos!$E$153 -> -4.2769562 | AA56: =-Energia!$E$20*(1-(1-Supuestos!$E$146)^(21-1))*Supuestos!$E$153 -> -4.4909732 | AB56: =-Energia!$E$20*(1-(1-Supuestos!$E$146)^(22-1))*Supuestos!$E$153 -> -4.7039201 | AC56: =-Energia!$E$20*(1-(1-Supuestos!$E$146)^(23-1))*Supuestos!$E$153 -> -4.9158024 | AD56: =-Energia!$E$20*(1-(1-Supuestos!$E$146)^(24-1))*Supuestos!$E$153 -> -5.1266252 | AE56: =-Energia!$E$20*(1-(1-Supuestos!$E$146)^(25-1))*Supuestos!$E$153 -> -5.3363938 | AF56: =-Energia!$E$20*(1-(1-Supuestos!$E$146)^(26-1))*Supuestos!$E$153 -> -5.5451137 | AG56: =-Energia!$E$20*(1-(1-Supuestos!$E$146)^(27-1))*Supuestos!$E$153 -> -5.7527899 | AH56: =-Energia!$E$20*(1-(1-Supuestos!$E$146)^(28-1))*Supuestos!$E$153 -> -5.9594278 | AI56: =-Energia!$E$20*(1-(1-Supuestos!$E$146)^(29-1))*Supuestos!$E$153 -> -6.1650325 | AJ56: =-Energia!$E$20*(1-(1-Supuestos!$E$146)^(30-1))*Supuestos!$E$153 -> -6.3696091
A57: EBITDA | C57: =C54+C55+C56 -> 0 | D57: =D54+D55+D56 -> 0 | E57: =E54+E55+E56 -> 0 | F57: =F54+F55+F56 -> 0 | G57: =G54+G55+G56 -> 5121.6202 | H57: =H54+H55+H56 -> 5871.3354 | I57: =I54+I55+I56 -> 5871.1012 | J57: =J54+J55+J56 -> 5870.8681 | ... AJ57: =AJ54+AJ55+AJ56 -> 5865.2012
A58: Depreciación fiscal | C58: 0 | D58: 0 | E58: 0 | F58: 0 | G58: =IF(1<=1/Supuestos!$E$22,(Supuestos!$E$8)*Supuestos!$E$22,0) -> 2662.25 | H58: =IF(2<=1/Supuestos!$E$22,(Supuestos!$E$8)*Supuestos!$E$22,0) -> 2662.25 | I58: =IF(3<=1/Supuestos!$E$22,(Supuestos!$E$8)*Supuestos!$E$22,0) -> 2662.25 | J58: =IF(4<=1/Supuestos!$E$22,(Supuestos!$E$8)*Supuestos!$E$22,0) -> 2662.25 | K58: =IF(5<=1/Supuestos!$E$22,(Supuestos!$E$8)*Supuestos!$E$22,0) -> 2662.25 | L58: =IF(6<=1/Supuestos!$E$22,(Supuestos!$E$8)*Supuestos!$E$22,0) -> 2662.25 | M58: =IF(7<=1/Supuestos!$E$22,(Supuestos!$E$8)*Supuestos!$E$22,0) -> 2662.25 | N58: =IF(8<=1/Supuestos!$E$22,(Supuestos!$E$8)*Supuestos!$E$22,0) -> 2662.25 | O58: =IF(9<=1/Supuestos!$E$22,(Supuestos!$E$8)*Supuestos!$E$22,0) -> 2662.25 | P58: =IF(10<=1/Supuestos!$E$22,(Supuestos!$E$8)*Supuestos!$E$22,0) -> 2662.25 | Q58: =IF(11<=1/Supuestos!$E$22,(Supuestos!$E$8)*Supuestos!$E$22,0) -> 2662.25 | R58: =IF(12<=1/Supuestos!$E$22,(Supuestos!$E$8)*Supuestos!$E$22,0) -> 2662.25 | S58: =IF(13<=1/Supuestos!$E$22,(Supuestos!$E$8)*Supuestos!$E$22,0) -> 2662.25 | T58: =IF(14<=1/Supuestos!$E$22,(Supuestos!$E$8)*Supuestos!$E$22,0) -> 2662.25 | U58: =IF(15<=1/Supuestos!$E$22,(Supuestos!$E$8)*Supuestos!$E$22,0) -> 2662.25 | V58: =IF(16<=1/Supuestos!$E$22,(Supuestos!$E$8)*Supuestos!$E$22,0) -> 2662.25 | W58: =IF(17<=1/Supuestos!$E$22,(Supuestos!$E$8)*Supuestos!$E$22,0) -> 2662.25 | X58: =IF(18<=1/Supuestos!$E$22,(Supuestos!$E$8)*Supuestos!$E$22,0) -> 2662.25 | Y58: =IF(19<=1/Supuestos!$E$22,(Supuestos!$E$8)*Supuestos!$E$22,0) -> 2662.25 | Z58: =IF(20<=1/Supuestos!$E$22,(Supuestos!$E$8)*Supuestos!$E$22,0) -> 2662.25 | AA58: =IF(21<=1/Supuestos!$E$22,(Supuestos!$E$8)*Supuestos!$E$22,0) -> 0 | AB58: =IF(22<=1/Supuestos!$E$22,(Supuestos!$E$8)*Supuestos!$E$22,0) -> 0 | AC58: =IF(23<=1/Supuestos!$E$22,(Supuestos!$E$8)*Supuestos!$E$22,0) -> 0 | AD58: =IF(24<=1/Supuestos!$E$22,(Supuestos!$E$8)*Supuestos!$E$22,0) -> 0 | AE58: =IF(25<=1/Supuestos!$E$22,(Supuestos!$E$8)*Supuestos!$E$22,0) -> 0 | AF58: =IF(26<=1/Supuestos!$E$22,(Supuestos!$E$8)*Supuestos!$E$22,0) -> 0 | AG58: =IF(27<=1/Supuestos!$E$22,(Supuestos!$E$8)*Supuestos!$E$22,0) -> 0 | AH58: =IF(28<=1/Supuestos!$E$22,(Supuestos!$E$8)*Supuestos!$E$22,0) -> 0 | AI58: =IF(29<=1/Supuestos!$E$22,(Supuestos!$E$8)*Supuestos!$E$22,0) -> 0 | AJ58: =IF(30<=1/Supuestos!$E$22,(Supuestos!$E$8)*Supuestos!$E$22,0) -> 0
A59: ISR | C59: =-MAX(0,C57-C58)*Supuestos!$E$21 -> 0 | D59: =-MAX(0,D57-D58)*Supuestos!$E$21 -> 0 | E59: =-MAX(0,E57-E58)*Supuestos!$E$21 -> 0 | F59: =-MAX(0,F57-F58)*Supuestos!$E$21 -> 0 | G59: =-MAX(0,G57-G58)*Supuestos!$E$21 -> -737.81106 | H59: =-MAX(0,H57-H58)*Supuestos!$E$21 -> -962.72562 | I59: =-MAX(0,I57-I58)*Supuestos!$E$21 -> -962.65535 | J59: =-MAX(0,J57-J58)*Supuestos!$E$21 -> -962.58543 | ... AJ59: =-MAX(0,AJ57-AJ58)*Supuestos!$E$21 -> -1759.5604
A60: Flujo antes de impuestos | C60: =C53+C57 -> -10699 | D60: =D53+D57 -> -16048.5 | E60: =E53+E57 -> -16048.5 | F60: =F53+F57 -> -10699 | G60: =G53+G57 -> 5121.6202 | H60: =H53+H57 -> 5871.3354 | I60: =I53+I57 -> 5871.1012 | J60: =J53+J57 -> 5870.8681 | ... AJ60: =AJ53+AJ57 -> 5865.2012
A61: Flujo después de impuestos | C61: =C60+C59 -> -10699 | D61: =D60+D59 -> -16048.5 | E61: =E60+E59 -> -16048.5 | F61: =F60+F59 -> -10699 | G61: =G60+G59 -> 4383.8091 | H61: =H60+H59 -> 4908.6098 | I61: =I60+I59 -> 4908.4458 | J61: =J60+J59 -> 4908.2827 | ... AJ61: =AJ60+AJ59 -> 4105.6408
A62: Acumulado | C62: =C61 -> -10699 | D62: =C62+D61 -> -26747.5 | E62: =D62+E61 -> -42796 | F62: =E62+F61 -> -53495 | G62: =F62+G61 -> -49111.191 | H62: =G62+H61 -> -44202.581 | I62: =H62+I61 -> -39294.135 | J62: =I62+J61 -> -34385.853 | K62: =J62+K61 -> -29477.732 | ... AJ62: =AI62+AJ61 -> 85188.076
A63: Flujo descontado | C63: =C61/(1+Supuestos!$E$20)^0 -> -10699 | D63: =D61/(1+Supuestos!$E$20)^1 -> -14998.598 | E63: =E61/(1+Supuestos!$E$20)^2 -> -14017.381 | F63: =F61/(1+Supuestos!$E$20)^3 -> -8733.571 | G63: =G61/(1+Supuestos!$E$20)^4 -> 3344.387 | H63: =H61/(1+Supuestos!$E$20)^5 -> 3499.7709 | I63: =I61/(1+Supuestos!$E$20)^6 -> 3270.7047 | J63: =J61/(1+Supuestos!$E$20)^7 -> 3056.6318 | K63: =K61/(1+Supuestos!$E$20)^8 -> 2856.5707 | L63: =L61/(1+Supuestos!$E$20)^9 -> 2669.6044 | M63: =M61/(1+Supuestos!$E$20)^10 -> 2494.8757 | N63: =N61/(1+Supuestos!$E$20)^11 -> 2331.5836 | O63: =O61/(1+Supuestos!$E$20)^12 -> 2178.9794 | P63: =P61/(1+Supuestos!$E$20)^13 -> 2036.3637 | Q63: =Q61/(1+Supuestos!$E$20)^14 -> 1903.0825 | R63: =R61/(1+Supuestos!$E$20)^15 -> 1778.525 | S63: =S61/(1+Supuestos!$E$20)^16 -> 1662.1201 | T63: =T61/(1+Supuestos!$E$20)^17 -> 1553.3341 | U63: =U61/(1+Supuestos!$E$20)^18 -> 1451.6685 | V63: =V61/(1+Supuestos!$E$20)^19 -> 1356.657 | W63: =W61/(1+Supuestos!$E$20)^20 -> 1267.8643 | X63: =X61/(1+Supuestos!$E$20)^21 -> 1184.8831 | Y63: =Y61/(1+Supuestos!$E$20)^22 -> 1107.3333 | Z63: =Z61/(1+Supuestos!$E$20)^23 -> 1034.8591 | AA63: =AA61/(1+Supuestos!$E$20)^24 -> 809.67247 | AB63: =AB61/(1+Supuestos!$E$20)^25 -> 756.67578 | AC63: =AC61/(1+Supuestos!$E$20)^26 -> 707.14808 | AD63: =AD61/(1+Supuestos!$E$20)^27 -> 660.86231 | AE63: =AE61/(1+Supuestos!$E$20)^28 -> 617.60624 | AF63: =AF61/(1+Supuestos!$E$20)^29 -> 577.18156 | AG63: =AG61/(1+Supuestos!$E$20)^30 -> 539.40292 | AH63: =AH61/(1+Supuestos!$E$20)^31 -> 504.09712 | AI63: =AI61/(1+Supuestos!$E$20)^32 -> 471.10229 | AJ63: =AJ61/(1+Supuestos!$E$20)^33 -> 440.26716
A64: Acumulado descontado | C64: =C63 -> -10699 | D64: =C64+D63 -> -25697.598 | E64: =D64+E63 -> -39714.98 | F64: =E64+F63 -> -48448.551 | G64: =F64+G63 -> -45104.164 | H64: =G64+H63 -> -41604.393 | I64: =H64+I63 -> -38333.688 | J64: =I64+J63 -> -35277.056 | K64: =J64+K63 -> -32420.485 | ... AJ64: =AI64+AJ63 -> -324.73558
A65: VPN a la tasa real (después de impuestos) | B65: =SUM(C63:AJ63) -> -324.73558
A66: TIR real antes de impuestos | B66: =IFERROR(IRR(C60:AJ60,0.02),IFERROR(IRR(C60:AJ60,-0.05),"negativa")) -> 0.087628617
A67: TIR real después de impuestos | B67: =IFERROR(IRR(C61:AJ61,0.02),IFERROR(IRR(C61:AJ61,-0.05),"negativa")) -> 0.069403752
A68: Recuperación (años desde la apertura) | B68: =IF(COUNTIF(G62:AJ62,"<0")>=30,"más de 30",COUNTIF(G62:AJ62,"<0")+1) -> 12
A69: Recuperación descontada (años desde la apertura) | B69: =IF(COUNTIF(G64:AJ64,"<0")>=30,"más de 30",COUNTIF(G64:AJ64,"<0")+1) -> más de 30
A70: Efectivo acumulado al año 30 | B70: =AJ62 -> 85188.076
A73: Escenario Base con APP
A74: Año | C74: Obra 1 | D74: Obra 2 | E74: Obra 3 | F74: Obra 4 | G74: 1 | H74: 2 | I74: 3 | J74: 4 | K74: 5 | L74: 6 | M74: 7 | N74: 8 | O74: 9 | P74: 10 | Q74: 11 | R74: 12 | S74: 13 | T74: 14 | U74: 15 | V74: 16 | W74: 17 | X74: 18 | Y74: 19 | Z74: 20 | AA74: 21 | AB74: 22 | AC74: 23 | AD74: 24 | AE74: 25 | AF74: 26 | AG74: 27 | AH74: 28 | AI74: 29 | AJ74: 30
A75: Fase | C75: =Supuestos!$D$14 -> 0.2 | D75: =Supuestos!$D$15 -> 0.3 | E75: =Supuestos!$D$16 -> 0.3 | F75: =Supuestos!$D$17 -> 0.2 | G75: =Supuestos!$D$18 -> 0.85 | H75: =Supuestos!$D$19 -> 0.95 | I75: 1 | J75: 1 | K75: 1 | L75: 1 | M75: 1 | N75: 1 | O75: 1 | P75: 1 | Q75: 1 | R75: 1 | S75: 1 | T75: 1 | U75: 1 | V75: 1 | W75: 1 | X75: 1 | Y75: 1 | Z75: 1 | AA75: 1 | AB75: 1 | AC75: 1 | AD75: 1 | AE75: 1 | AF75: 1 | AG75: 1 | AH75: 1 | AI75: 1 | AJ75: 1
A76: Inversión | C76: =-(Supuestos!$D$8+Supuestos!$D$13-Supuestos!$D$12*Supuestos!$D$23)*C75 -> -7045.8 | D76: =-(Supuestos!$D$8+Supuestos!$D$13-Supuestos!$D$12*Supuestos!$D$23)*D75 -> -10568.7 | E76: =-(Supuestos!$D$8+Supuestos!$D$13-Supuestos!$D$12*Supuestos!$D$23)*E75 -> -10568.7 | F76: =-(Supuestos!$D$8+Supuestos!$D$13-Supuestos!$D$12*Supuestos!$D$23)*F75 -> -7045.8 | G76: 0 | H76: 0 | I76: 0 | J76: 0 | K76: 0 | L76: 0 | M76: 0 | N76: 0 | O76: 0 | P76: 0 | Q76: 0 | R76: 0 | S76: 0 | T76: 0 | U76: 0 | V76: 0 | W76: 0 | X76: 0 | Y76: 0 | Z76: 0 | AA76: 0 | AB76: 0 | AC76: 0 | AD76: 0 | AE76: 0 | AF76: 0 | AG76: 0 | AH76: 0 | AI76: 0 | AJ76: 0
A77: Ingresos | C77: 0 | D77: 0 | E77: 0 | F77: 0 | G77: =Ingresos!$D$68*G75 -> 3796.4719 | H77: =Ingresos!$D$68*H75 -> 4243.1156 | I77: =Ingresos!$D$68*I75 -> 4466.4375 | J77: =Ingresos!$D$68*J75 -> 4466.4375 | K77: =Ingresos!$D$68*K75 -> 4466.4375 | L77: =Ingresos!$D$68*L75 -> 4466.4375 | M77: =Ingresos!$D$68*M75 -> 4466.4375 | N77: =Ingresos!$D$68*N75 -> 4466.4375 | ... AJ77: =Ingresos!$D$68*AJ75 -> 4466.4375
A78: Costos de operación | C78: 0 | D78: 0 | E78: 0 | F78: 0 | G78: =-Costos_Operacion!$D$42 -> -1718.0966 | H78: =-Costos_Operacion!$D$42 -> -1718.0966 | I78: =-Costos_Operacion!$D$42 -> -1718.0966 | J78: =-Costos_Operacion!$D$42 -> -1718.0966 | K78: =-Costos_Operacion!$D$42 -> -1718.0966 | L78: =-Costos_Operacion!$D$42 -> -1718.0966 | M78: =-Costos_Operacion!$D$42 -> -1718.0966 | N78: =-Costos_Operacion!$D$42 -> -1718.0966 | ... AJ78: =-Costos_Operacion!$D$42 -> -1718.0966
A79: Energía extra por degradación de paneles | C79: 0 | D79: 0 | E79: 0 | F79: 0 | G79: =-Energia!$D$20*(1-(1-Supuestos!$D$146)^(1-1))*Supuestos!$D$153 -> 0 | H79: =-Energia!$D$20*(1-(1-Supuestos!$D$146)^(2-1))*Supuestos!$D$153 -> -0.22294649 | I79: =-Energia!$D$20*(1-(1-Supuestos!$D$146)^(3-1))*Supuestos!$D$153 -> -0.44477825 | J79: =-Energia!$D$20*(1-(1-Supuestos!$D$146)^(4-1))*Supuestos!$D$153 -> -0.66550085 | K79: =-Energia!$D$20*(1-(1-Supuestos!$D$146)^(5-1))*Supuestos!$D$153 -> -0.88511984 | L79: =-Energia!$D$20*(1-(1-Supuestos!$D$146)^(6-1))*Supuestos!$D$153 -> -1.1036407 | M79: =-Energia!$D$20*(1-(1-Supuestos!$D$146)^(7-1))*Supuestos!$D$153 -> -1.321069 | N79: =-Energia!$D$20*(1-(1-Supuestos!$D$146)^(8-1))*Supuestos!$D$153 -> -1.5374102 | O79: =-Energia!$D$20*(1-(1-Supuestos!$D$146)^(9-1))*Supuestos!$D$153 -> -1.7526696 | P79: =-Energia!$D$20*(1-(1-Supuestos!$D$146)^(10-1))*Supuestos!$D$153 -> -1.9668527 | Q79: =-Energia!$D$20*(1-(1-Supuestos!$D$146)^(11-1))*Supuestos!$D$153 -> -2.179965 | R79: =-Energia!$D$20*(1-(1-Supuestos!$D$146)^(12-1))*Supuestos!$D$153 -> -2.3920116 | S79: =-Energia!$D$20*(1-(1-Supuestos!$D$146)^(13-1))*Supuestos!$D$153 -> -2.6029981 | T79: =-Energia!$D$20*(1-(1-Supuestos!$D$146)^(14-1))*Supuestos!$D$153 -> -2.8129296 | U79: =-Energia!$D$20*(1-(1-Supuestos!$D$146)^(15-1))*Supuestos!$D$153 -> -3.0218114 | V79: =-Energia!$D$20*(1-(1-Supuestos!$D$146)^(16-1))*Supuestos!$D$153 -> -3.2296488 | W79: =-Energia!$D$20*(1-(1-Supuestos!$D$146)^(17-1))*Supuestos!$D$153 -> -3.4364471 | X79: =-Energia!$D$20*(1-(1-Supuestos!$D$146)^(18-1))*Supuestos!$D$153 -> -3.6422113 | Y79: =-Energia!$D$20*(1-(1-Supuestos!$D$146)^(19-1))*Supuestos!$D$153 -> -3.8469468 | Z79: =-Energia!$D$20*(1-(1-Supuestos!$D$146)^(20-1))*Supuestos!$D$153 -> -4.0506585 | AA79: =-Energia!$D$20*(1-(1-Supuestos!$D$146)^(21-1))*Supuestos!$D$153 -> -4.2533517 | AB79: =-Energia!$D$20*(1-(1-Supuestos!$D$146)^(22-1))*Supuestos!$D$153 -> -4.4550315 | AC79: =-Energia!$D$20*(1-(1-Supuestos!$D$146)^(23-1))*Supuestos!$D$153 -> -4.6557028 | AD79: =-Energia!$D$20*(1-(1-Supuestos!$D$146)^(24-1))*Supuestos!$D$153 -> -4.8553708 | AE79: =-Energia!$D$20*(1-(1-Supuestos!$D$146)^(25-1))*Supuestos!$D$153 -> -5.0540404 | AF79: =-Energia!$D$20*(1-(1-Supuestos!$D$146)^(26-1))*Supuestos!$D$153 -> -5.2517167 | AG79: =-Energia!$D$20*(1-(1-Supuestos!$D$146)^(27-1))*Supuestos!$D$153 -> -5.4484046 | AH79: =-Energia!$D$20*(1-(1-Supuestos!$D$146)^(28-1))*Supuestos!$D$153 -> -5.6441091 | AI79: =-Energia!$D$20*(1-(1-Supuestos!$D$146)^(29-1))*Supuestos!$D$153 -> -5.838835 | AJ79: =-Energia!$D$20*(1-(1-Supuestos!$D$146)^(30-1))*Supuestos!$D$153 -> -6.0325873
A80: EBITDA | C80: =C77+C78+C79 -> 0 | D80: =D77+D78+D79 -> 0 | E80: =E77+E78+E79 -> 0 | F80: =F77+F78+F79 -> 0 | G80: =G77+G78+G79 -> 2078.3753 | H80: =H77+H78+H79 -> 2524.7961 | I80: =I77+I78+I79 -> 2747.8961 | J80: =J77+J78+J79 -> 2747.6754 | ... AJ80: =AJ77+AJ78+AJ79 -> 2742.3083
A81: Depreciación fiscal | C81: 0 | D81: 0 | E81: 0 | F81: 0 | G81: =IF(1<=1/Supuestos!$D$22,(Supuestos!$D$8-Supuestos!$D$12*Supuestos!$D$23)*Supuestos!$D$22,0) -> 1746.45 | H81: =IF(2<=1/Supuestos!$D$22,(Supuestos!$D$8-Supuestos!$D$12*Supuestos!$D$23)*Supuestos!$D$22,0) -> 1746.45 | I81: =IF(3<=1/Supuestos!$D$22,(Supuestos!$D$8-Supuestos!$D$12*Supuestos!$D$23)*Supuestos!$D$22,0) -> 1746.45 | J81: =IF(4<=1/Supuestos!$D$22,(Supuestos!$D$8-Supuestos!$D$12*Supuestos!$D$23)*Supuestos!$D$22,0) -> 1746.45 | K81: =IF(5<=1/Supuestos!$D$22,(Supuestos!$D$8-Supuestos!$D$12*Supuestos!$D$23)*Supuestos!$D$22,0) -> 1746.45 | L81: =IF(6<=1/Supuestos!$D$22,(Supuestos!$D$8-Supuestos!$D$12*Supuestos!$D$23)*Supuestos!$D$22,0) -> 1746.45 | M81: =IF(7<=1/Supuestos!$D$22,(Supuestos!$D$8-Supuestos!$D$12*Supuestos!$D$23)*Supuestos!$D$22,0) -> 1746.45 | N81: =IF(8<=1/Supuestos!$D$22,(Supuestos!$D$8-Supuestos!$D$12*Supuestos!$D$23)*Supuestos!$D$22,0) -> 1746.45 | O81: =IF(9<=1/Supuestos!$D$22,(Supuestos!$D$8-Supuestos!$D$12*Supuestos!$D$23)*Supuestos!$D$22,0) -> 1746.45 | P81: =IF(10<=1/Supuestos!$D$22,(Supuestos!$D$8-Supuestos!$D$12*Supuestos!$D$23)*Supuestos!$D$22,0) -> 1746.45 | Q81: =IF(11<=1/Supuestos!$D$22,(Supuestos!$D$8-Supuestos!$D$12*Supuestos!$D$23)*Supuestos!$D$22,0) -> 1746.45 | R81: =IF(12<=1/Supuestos!$D$22,(Supuestos!$D$8-Supuestos!$D$12*Supuestos!$D$23)*Supuestos!$D$22,0) -> 1746.45 | S81: =IF(13<=1/Supuestos!$D$22,(Supuestos!$D$8-Supuestos!$D$12*Supuestos!$D$23)*Supuestos!$D$22,0) -> 1746.45 | T81: =IF(14<=1/Supuestos!$D$22,(Supuestos!$D$8-Supuestos!$D$12*Supuestos!$D$23)*Supuestos!$D$22,0) -> 1746.45 | U81: =IF(15<=1/Supuestos!$D$22,(Supuestos!$D$8-Supuestos!$D$12*Supuestos!$D$23)*Supuestos!$D$22,0) -> 1746.45 | V81: =IF(16<=1/Supuestos!$D$22,(Supuestos!$D$8-Supuestos!$D$12*Supuestos!$D$23)*Supuestos!$D$22,0) -> 1746.45 | W81: =IF(17<=1/Supuestos!$D$22,(Supuestos!$D$8-Supuestos!$D$12*Supuestos!$D$23)*Supuestos!$D$22,0) -> 1746.45 | X81: =IF(18<=1/Supuestos!$D$22,(Supuestos!$D$8-Supuestos!$D$12*Supuestos!$D$23)*Supuestos!$D$22,0) -> 1746.45 | Y81: =IF(19<=1/Supuestos!$D$22,(Supuestos!$D$8-Supuestos!$D$12*Supuestos!$D$23)*Supuestos!$D$22,0) -> 1746.45 | Z81: =IF(20<=1/Supuestos!$D$22,(Supuestos!$D$8-Supuestos!$D$12*Supuestos!$D$23)*Supuestos!$D$22,0) -> 1746.45 | AA81: =IF(21<=1/Supuestos!$D$22,(Supuestos!$D$8-Supuestos!$D$12*Supuestos!$D$23)*Supuestos!$D$22,0) -> 0 | AB81: =IF(22<=1/Supuestos!$D$22,(Supuestos!$D$8-Supuestos!$D$12*Supuestos!$D$23)*Supuestos!$D$22,0) -> 0 | AC81: =IF(23<=1/Supuestos!$D$22,(Supuestos!$D$8-Supuestos!$D$12*Supuestos!$D$23)*Supuestos!$D$22,0) -> 0 | AD81: =IF(24<=1/Supuestos!$D$22,(Supuestos!$D$8-Supuestos!$D$12*Supuestos!$D$23)*Supuestos!$D$22,0) -> 0 | AE81: =IF(25<=1/Supuestos!$D$22,(Supuestos!$D$8-Supuestos!$D$12*Supuestos!$D$23)*Supuestos!$D$22,0) -> 0 | AF81: =IF(26<=1/Supuestos!$D$22,(Supuestos!$D$8-Supuestos!$D$12*Supuestos!$D$23)*Supuestos!$D$22,0) -> 0 | AG81: =IF(27<=1/Supuestos!$D$22,(Supuestos!$D$8-Supuestos!$D$12*Supuestos!$D$23)*Supuestos!$D$22,0) -> 0 | AH81: =IF(28<=1/Supuestos!$D$22,(Supuestos!$D$8-Supuestos!$D$12*Supuestos!$D$23)*Supuestos!$D$22,0) -> 0 | AI81: =IF(29<=1/Supuestos!$D$22,(Supuestos!$D$8-Supuestos!$D$12*Supuestos!$D$23)*Supuestos!$D$22,0) -> 0 | AJ81: =IF(30<=1/Supuestos!$D$22,(Supuestos!$D$8-Supuestos!$D$12*Supuestos!$D$23)*Supuestos!$D$22,0) -> 0
A82: ISR | C82: =-MAX(0,C80-C81)*Supuestos!$D$21 -> 0 | D82: =-MAX(0,D80-D81)*Supuestos!$D$21 -> 0 | E82: =-MAX(0,E80-E81)*Supuestos!$D$21 -> 0 | F82: =-MAX(0,F80-F81)*Supuestos!$D$21 -> 0 | G82: =-MAX(0,G80-G81)*Supuestos!$D$21 -> -99.577589 | H82: =-MAX(0,H80-H81)*Supuestos!$D$21 -> -233.50383 | I82: =-MAX(0,I80-I81)*Supuestos!$D$21 -> -300.43384 | J82: =-MAX(0,J80-J81)*Supuestos!$D$21 -> -300.36763 | ... AJ82: =-MAX(0,AJ80-AJ81)*Supuestos!$D$21 -> -822.6925
A83: Flujo antes de impuestos | C83: =C76+C80 -> -7045.8 | D83: =D76+D80 -> -10568.7 | E83: =E76+E80 -> -10568.7 | F83: =F76+F80 -> -7045.8 | G83: =G76+G80 -> 2078.3753 | H83: =H76+H80 -> 2524.7961 | I83: =I76+I80 -> 2747.8961 | J83: =J76+J80 -> 2747.6754 | ... AJ83: =AJ76+AJ80 -> 2742.3083
A84: Flujo después de impuestos | C84: =C83+C82 -> -7045.8 | D84: =D83+D82 -> -10568.7 | E84: =E83+E82 -> -10568.7 | F84: =F83+F82 -> -7045.8 | G84: =G83+G82 -> 1978.7977 | H84: =H83+H82 -> 2291.2923 | I84: =I83+I82 -> 2447.4623 | J84: =J83+J82 -> 2447.3078 | ... AJ84: =AJ83+AJ82 -> 1919.6158
A85: Acumulado | C85: =C84 -> -7045.8 | D85: =C85+D84 -> -17614.5 | E85: =D85+E84 -> -28183.2 | F85: =E85+F84 -> -35229 | G85: =F85+G84 -> -33250.202 | H85: =G85+H84 -> -30958.91 | I85: =H85+I84 -> -28511.448 | J85: =I85+J84 -> -26064.14 | K85: =J85+K84 -> -23616.986 | ... AJ85: =AI85+AJ84 -> 32274.735
A86: Flujo descontado | C86: =C84/(1+Supuestos!$D$20)^0 -> -7045.8 | D86: =D84/(1+Supuestos!$D$20)^1 -> -9785.8333 | E86: =E84/(1+Supuestos!$D$20)^2 -> -9060.9568 | F86: =F84/(1+Supuestos!$D$20)^3 -> -5593.1832 | G86: =G84/(1+Supuestos!$D$20)^4 -> 1454.4754 | H86: =H84/(1+Supuestos!$D$20)^5 -> 1559.415 | I86: =I84/(1+Supuestos!$D$20)^6 -> 1542.3164 | J86: =J84/(1+Supuestos!$D$20)^7 -> 1427.9806 | K86: =K84/(1+Supuestos!$D$20)^8 -> 1322.1212 | L86: =L84/(1+Supuestos!$D$20)^9 -> 1224.1098 | M86: =M84/(1+Supuestos!$D$20)^10 -> 1133.3645 | N86: =N84/(1+Supuestos!$D$20)^11 -> 1049.3466 | O86: =O84/(1+Supuestos!$D$20)^12 -> 971.55739 | P86: =P84/(1+Supuestos!$D$20)^13 -> 899.53504 | Q86: =Q84/(1+Supuestos!$D$20)^14 -> 832.85203 | R86: =R84/(1+Supuestos!$D$20)^15 -> 771.11249 | S86: =S84/(1+Supuestos!$D$20)^16 -> 713.94994 | T86: =T84/(1+Supuestos!$D$20)^17 -> 661.02504 | U86: =U84/(1+Supuestos!$D$20)^18 -> 612.02363 | V86: =V84/(1+Supuestos!$D$20)^19 -> 566.65484 | W86: =W84/(1+Supuestos!$D$20)^20 -> 524.64935 | X86: =X84/(1+Supuestos!$D$20)^21 -> 485.75782 | Y86: =Y84/(1+Supuestos!$D$20)^22 -> 449.7494 | Z86: =Z84/(1+Supuestos!$D$20)^23 -> 416.41034 | AA86: =AA84/(1+Supuestos!$D$20)^24 -> 302.91855 | AB86: =AB84/(1+Supuestos!$D$20)^25 -> 280.45953 | AC86: =AC84/(1+Supuestos!$D$20)^26 -> 259.66576 | AD86: =AD84/(1+Supuestos!$D$20)^27 -> 240.41376 | AE86: =AE84/(1+Supuestos!$D$20)^28 -> 222.58921 | AF86: =AF84/(1+Supuestos!$D$20)^29 -> 206.08627 | AG86: =AG84/(1+Supuestos!$D$20)^30 -> 190.80694 | AH86: =AH84/(1+Supuestos!$D$20)^31 -> 176.66049 | AI86: =AI84/(1+Supuestos!$D$20)^32 -> 163.56291 | AJ86: =AJ84/(1+Supuestos!$D$20)^33 -> 151.43644
A87: Acumulado descontado | C87: =C86 -> -7045.8 | D87: =C87+D86 -> -16831.633 | E87: =D87+E86 -> -25892.59 | F87: =E87+F86 -> -31485.773 | G87: =F87+G86 -> -30031.298 | H87: =G87+H86 -> -28471.883 | I87: =H87+I86 -> -26929.567 | J87: =I87+J86 -> -25501.586 | K87: =J87+K86 -> -24179.465 | ... AJ87: =AI87+AJ86 -> -10672.767
A88: VPN a la tasa real (después de impuestos) | B88: =SUM(C86:AJ86) -> -10672.767
A89: TIR real antes de impuestos | B89: =IFERROR(IRR(C83:AJ83,0.02),IFERROR(IRR(C83:AJ83,-0.05),"negativa")) -> 0.056720628
A90: TIR real después de impuestos | B90: =IFERROR(IRR(C84:AJ84,0.02),IFERROR(IRR(C84:AJ84,-0.05),"negativa")) -> 0.044712836
A91: Recuperación (años desde la apertura) | B91: =IF(COUNTIF(G85:AJ85,"<0")>=30,"más de 30",COUNTIF(G85:AJ85,"<0")+1) -> 15
A92: Recuperación descontada (años desde la apertura) | B92: =IF(COUNTIF(G87:AJ87,"<0")>=30,"más de 30",COUNTIF(G87:AJ87,"<0")+1) -> más de 30
A93: Efectivo acumulado al año 30 | B93: =AJ85 -> 32274.735

Sheet Derrama
A1: Derrama económica: lo que mueve en la ciudad
A2: No es ganancia del dueño: es el dinero y los empleos que el proyecto genera alrededor. Millones de MXN por año.
A4: Concepto | B4: Unidad | C4: Conservador | D4: Base | E4: Optimista | F4: Nota / fuente
A6: Gente
A7: Asistentes a eventos | B7: personas/año | C7: =Eventos!$C$64 -> 2195000 | D7: =Eventos!$D$64 -> 3742000 | E7: =Eventos!$E$64 -> 5805000
A8: Visitantes de la plaza | B8: personas/año | C8: =Supuestos!$C$202*365 -> 12775000 | D8: =Supuestos!$D$202*365 -> 16425000 | E8: =Supuestos!$E$202*365 -> 20075000
A10: Dinero que se mueve al año
A11: Taquillas de todos los eventos | B11: M MXN/año | C11: =Eventos!$C$66 -> 1976.5 | D11: =Eventos!$D$66 -> 4563.6 | E11: =Eventos!$E$66 -> 8948
A12: Alimentos, bebidas y mercancía dentro del estadio | B12: M MXN/año | C12: =Eventos!$C$67+Eventos!$C$68 -> 530.35 | D12: =Eventos!$D$67+Eventos!$D$68 -> 1193.56 | E12: =Eventos!$E$67+Eventos!$E$68 -> 2427
A13: Gasto de asistentes fuera del estadio | B13: M MXN/año | C13: =Eventos!$C$64*Supuestos!$C$203/10^6 -> 658.5 | D13: =Eventos!$D$64*Supuestos!$D$203/10^6 -> 1496.8 | E13: =Eventos!$E$64*Supuestos!$E$203/10^6 -> 2902.5
A14: Hoteles y comidas de visitantes foráneos | B14: M MXN/año | C14: =Eventos!$C$64*Supuestos!$C$204*Supuestos!$C$205/10^6 -> 395.1 | D14: =Eventos!$D$64*Supuestos!$D$204*Supuestos!$D$205/10^6 -> 1234.86 | E14: =Eventos!$E$64*Supuestos!$E$204*Supuestos!$E$205/10^6 -> 3018.6
A15: Ventas de los locatarios de la plaza | B15: M MXN/año | C15: =(Ingresos!$C$41+Ingresos!$C$42+Ingresos!$C$43+Ingresos!$C$44+Ingresos!$C$45+Ingresos!$C$47)/Supuestos!$C$206 -> 6997.564 | D15: =(Ingresos!$D$41+Ingresos!$D$42+Ingresos!$D$43+Ingresos!$D$44+Ingresos!$D$45+Ingresos!$D$47)/Supuestos!$D$206 -> 12245.179 | E15: =(Ingresos!$E$41+Ingresos!$E$42+Ingresos!$E$43+Ingresos!$E$44+Ingresos!$E$45+Ingresos!$E$47)/Supuestos!$E$206 -> 18190.322 | F15: Renta ÷ costo de ocupación
A16: Ingresos del dueño | B16: M MXN/año | C16: =Ingresos!$C$68 -> 2498.366 | D16: =Ingresos!$D$68 -> 4466.4375 | E16: =Ingresos!$E$68 -> 7499.5059
A17: Derrama total al año | B17: M MXN/año | C17: =Derrama!$C$11+Derrama!$C$12+Derrama!$C$13+Derrama!$C$14+Derrama!$C$15+Derrama!$C$16 -> 13056.38 | D17: =Derrama!$D$11+Derrama!$D$12+Derrama!$D$13+Derrama!$D$14+Derrama!$D$15+Derrama!$D$16 -> 25200.437 | E17: =Derrama!$E$11+Derrama!$E$12+Derrama!$E$13+Derrama!$E$14+Derrama!$E$15+Derrama!$E$16 -> 42985.928 | F17: Suma simple, sin multiplicador
A19: Empleos
A20: Empleos permanentes en la plaza | B20: empleos | C20: =Supuestos!$C$102*Supuestos!$C$103*Supuestos!$C$116/Supuestos!$C$207 -> 4361.8912 | D20: =Supuestos!$D$102*Supuestos!$D$103*Supuestos!$D$116/Supuestos!$D$207 -> 5646.4785 | E20: =Supuestos!$E$102*Supuestos!$E$103*Supuestos!$E$116/Supuestos!$E$207 -> 7126.0075
A21: Empleos permanentes del estadio | B21: empleos | C21: =Supuestos!$C$178 -> 220 | D21: =Supuestos!$D$178 -> 180 | E21: =Supuestos!$E$178 -> 170
A22: Empleos permanentes | B22: empleos | C22: =Derrama!$C$20+Derrama!$C$21 -> 4581.8912 | D22: =Derrama!$D$20+Derrama!$D$21 -> 5826.4785 | E22: =Derrama!$E$20+Derrama!$E$21 -> 7296.0075
A23: Empleos por día de evento | B23: personas | C23: =Supuestos!$C$72 -> 2800 | D23: =Supuestos!$D$72 -> 2500 | E23: =Supuestos!$E$72 -> 2200 | F23: Más el personal del concesionario y del promotor
A24: Empleos promedio durante la obra (4 años) | B24: empleos | C24: =Supuestos!$C$8*10^6*Supuestos!$C$208/Supuestos!$C$209/4 -> 16269.306 | D24: =Supuestos!$D$8*10^6*Supuestos!$D$208/Supuestos!$D$209/4 -> 16269.306 | E24: =Supuestos!$E$8*10^6*Supuestos!$E$208/Supuestos!$E$209/4 -> 16269.306
A26: Impuestos que genera
A27: IVA sobre ventas del dueño, taquillas y locatarios | B27: M MXN/año | C27: =(Derrama!$C$16+Derrama!$C$11+Derrama!$C$12+Derrama!$C$15)*Supuestos!$C$210 -> 1920.4448 | D27: =(Derrama!$D$16+Derrama!$D$11+Derrama!$D$12+Derrama!$D$15)*Supuestos!$D$210 -> 3595.0043 | E27: =(Derrama!$E$16+Derrama!$E$11+Derrama!$E$12+Derrama!$E$15)*Supuestos!$E$210 -> 5930.3724
A28: Predial | B28: M MXN/año | C28: =Costos_Operacion!$C$37 -> 53.245 | D28: =Costos_Operacion!$D$37 -> 53.245 | E28: =Costos_Operacion!$E$37 -> 42.596
A29: IVA de la obra (una sola vez) | B29: M MXN | C29: =Supuestos!$C$8*Supuestos!$C$210 -> 8519.2 | D29: =Supuestos!$D$8*Supuestos!$D$210 -> 8519.2 | E29: =Supuestos!$E$8*Supuestos!$E$210 -> 8519.2
